<?xml version="1.0" encoding="UTF-8"?>
<Gamebook><GamebookSummary Title="National Football League Game Summary" AuxiliaryTitle="" Copyright="NFL Copyright © 2003 by The National Football League. All rights reserved. This summary and play-by-play is for the express purpose of assisting media in their coverage of the game; any other use of this material is prohibited without the written permission of the National Football League." ScheduleDate="9/7/2003" VisitingTeam="Indianapolis Colts" HomeTeam="Cleveland Browns" StartTime="13:06" TimeZone="EST" Stadium="Cleveland Browns Stadium" StadiumType="outdoors" GameWeather="Sunny" Temperature="73" Humidity="42" WindSpeed="light/vrbl" TurfType="Grass" OutdoorWeather="Sunny" WindChill="n/a" WindDirection="" Referee="Walt Anderson (66)" Umpire="Carl Paganelli (124)" HeadLinesman="Tony Veteri (36)" LineJudge="Gary Arthur (108)" SideJudge="Jeff Lamberth (103)" BackJudge="Tony Steratore (112)" FieldJudge="Bill Lovett (98)" ReplayOfficial="Al Hynes" VideoOperator="Lou Nazzaro" Attendance="73,358" GameLength="2:41" VisitorScoreQ1="0" VisitorScoreQ2="3" VisitorScoreQ3="3" VisitorScoreQ4="3" VisitorScoreOT="0" HomeScoreQ1="3" HomeScoreQ2="0" HomeScoreQ3="0" HomeScoreQ4="3" HomeScoreOT="0"><OffensiveStarterHome Player="Q.Morgan" Position="WR" UniformNumber="81"/><OffensiveStarterHome Player="B.Stokes" Position="LT" UniformNumber="79"/><OffensiveStarterHome Player="M.Fowler" Position="LG" UniformNumber="67"/><OffensiveStarterHome Player="J.Faine" Position="C" UniformNumber="50"/><OffensiveStarterHome Player="S.O'Hara" Position="RG" UniformNumber="60"/><OffensiveStarterHome Player="R.Tucker" Position="RT" UniformNumber="72"/><OffensiveStarterHome Player="S.Heiden" Position="TE" UniformNumber="82"/><OffensiveStarterHome Player="K.Johnson" Position="WR" UniformNumber="85"/><OffensiveStarterHome Player="K.Holcomb" Position="QB" UniformNumber="10"/><OffensiveStarterHome Player="W.Green" Position="RB" UniformNumber="31"/><OffensiveStarterHome Player="A.Shea" Position="HB" UniformNumber="80"/><DefensiveStarterHome Player="C.Brown" Position="LE" UniformNumber="92"/><DefensiveStarterHome Player="G.Warren" Position="LT" UniformNumber="94"/><DefensiveStarterHome Player="O.Roye" Position="RT" UniformNumber="99"/><DefensiveStarterHome Player="K.Lang" Position="RE" UniformNumber="96"/><DefensiveStarterHome Player="K.Bentley" Position="SLB" UniformNumber="59"/><DefensiveStarterHome Player="A.Davis" Position="MLB" UniformNumber="54"/><DefensiveStarterHome Player="B.Taylor" Position="WLB" UniformNumber="58"/><DefensiveStarterHome Player="A.Henry" Position="LCB" UniformNumber="37"/><DefensiveStarterHome Player="D.McCutcheon" Position="RCB" UniformNumber="33"/><DefensiveStarterHome Player="R.Griffith" Position="SS" UniformNumber="24"/><DefensiveStarterHome Player="E.Little" Position="FS" UniformNumber="20"/><SubstitutionsHome Player="P.Dawson" Position="K" UniformNumber="4"/><SubstitutionsHome Player="C.Gardocki" Position="P" UniformNumber="17"/><SubstitutionsHome Player="L.Sanders" Position="DB" UniformNumber="21"/><SubstitutionsHome Player="M.Jameson" Position="DB" UniformNumber="22"/><SubstitutionsHome Player="C.Crocker" Position="DB" UniformNumber="25"/><SubstitutionsHome Player="L.Bodden" Position="DB" UniformNumber="28"/><SubstitutionsHome Player="J.Jackson" Position="RB" UniformNumber="29"/><SubstitutionsHome Player="J.White" Position="RB" UniformNumber="30"/><SubstitutionsHome Player="C.Thompson" Position="LB" UniformNumber="51"/><SubstitutionsHome Player="B.Boyer" Position="LB" UniformNumber="52"/><SubstitutionsHome Player="B.Gardner" Position="LB" UniformNumber="55"/><SubstitutionsHome Player="S.Coates" Position="LB" UniformNumber="56"/><SubstitutionsHome Player="R.Pontbriand" Position="LS" UniformNumber="64"/><SubstitutionsHome Player="P.Zukauskas" Position="OL" UniformNumber="66"/><SubstitutionsHome Player="J.Gonzalez" Position="OL" UniformNumber="73"/><SubstitutionsHome Player="A.King" Position="WR" UniformNumber="84"/><SubstitutionsHome Player="D.Northcutt" Position="WR" UniformNumber="86"/><SubstitutionsHome Player="A.Davis" Position="WR" UniformNumber="87"/><SubstitutionsHome Player="D.Sanders" Position="TE" UniformNumber="89"/><SubstitutionsHome Player="M.Word" Position="DL" UniformNumber="90"/><SubstitutionsHome Player="F.Claybrooks" Position="DL" UniformNumber="91"/><SubstitutionsHome Player="A.McKinley" Position="DL" UniformNumber="97"/><DidNotPlayHome Player="T.Couch" Position="QB" UniformNumber="2"/><NotActiveHome Player="J.Booty" Position="3QB" UniformNumber="12"/><NotActiveHome Player="C.Jones" Position="WR" UniformNumber="23"/><NotActiveHome Player="M.Lehan" Position="DB" UniformNumber="39"/><NotActiveHome Player="K.McLeod" Position="FB" UniformNumber="48"/><NotActiveHome Player="C.Beasley" Position="OL" UniformNumber="68"/><NotActiveHome Player="E.Demar" Position="OL" UniformNumber="70"/><NotActiveHome Player="T.Rogers" Position="DL" UniformNumber="78"/><NotActiveHome Player="A.Garay" Position="DL" UniformNumber="95"/><OffensiveStarterVisitor Player="R.Wayne" Position="WR" UniformNumber="87"/><OffensiveStarterVisitor Player="T.Glenn" Position="LT" UniformNumber="78"/><OffensiveStarterVisitor Player="R.DeMulling" Position="LG" UniformNumber="64"/><OffensiveStarterVisitor Player="J.Saturday" Position="C" UniformNumber="63"/><OffensiveStarterVisitor Player="S.Sciullo" Position="RG" UniformNumber="74"/><OffensiveStarterVisitor Player="R.Diem" Position="RT" UniformNumber="71"/><OffensiveStarterVisitor Player="D.Clark" Position="TE" UniformNumber="44"/><OffensiveStarterVisitor Player="M.Harrison" Position="WR" UniformNumber="88"/><OffensiveStarterVisitor Player="P.Manning" Position="QB" UniformNumber="18"/><OffensiveStarterVisitor Player="E.James" Position="RB" UniformNumber="32"/><OffensiveStarterVisitor Player="R.Williams" Position="WR" UniformNumber="35"/><DefensiveStarterVisitor Player="R.Brock" Position="LE" UniformNumber="79"/><DefensiveStarterVisitor Player="L.Tripplett" Position="LT" UniformNumber="75"/><DefensiveStarterVisitor Player="M.Reagor" Position="RT" UniformNumber="90"/><DefensiveStarterVisitor Player="D.Freeney" Position="RE" UniformNumber="93"/><DefensiveStarterVisitor Player="M.Washington" Position="LLB" UniformNumber="53"/><DefensiveStarterVisitor Player="R.Morris" Position="MLB" UniformNumber="94"/><DefensiveStarterVisitor Player="D.Thornton" Position="RLB" UniformNumber="50"/><DefensiveStarterVisitor Player="W.Harris" Position="LCB" UniformNumber="21"/><DefensiveStarterVisitor Player="N.Harper" Position="RCB" UniformNumber="25"/><DefensiveStarterVisitor Player="M.Doss" Position="SS" UniformNumber="20"/><DefensiveStarterVisitor Player="I.Bashir" Position="FS" UniformNumber="28"/><SubstitutionsVisitor Player="M.Vanderjagt" Position="K" UniformNumber="13"/><SubstitutionsVisitor Player="H.Smith" Position="P" UniformNumber="17"/><SubstitutionsVisitor Player="D.Macklin" Position="DB" UniformNumber="27"/><SubstitutionsVisitor Player="C.Crosby" Position="DB" UniformNumber="31"/><SubstitutionsVisitor Player="J.Doering" Position="DB" UniformNumber="34"/><SubstitutionsVisitor Player="C.Bird" Position="DB" UniformNumber="41"/><SubstitutionsVisitor Player="D.Smith" Position="RB" UniformNumber="42"/><SubstitutionsVisitor Player="B.Allen" Position="RB" UniformNumber="43"/><SubstitutionsVisitor Player="J.Snow" Position="TE" UniformNumber="48"/><SubstitutionsVisitor Player="T.Peko" Position="C/G" UniformNumber="56"/><SubstitutionsVisitor Player="J.Nelson" Position="LB" UniformNumber="57"/><SubstitutionsVisitor Player="G.Brackett" Position="LB" UniformNumber="58"/><SubstitutionsVisitor Player="A.Meadows" Position="OT" UniformNumber="73"/><SubstitutionsVisitor Player="J.Davenport" Position="TE" UniformNumber="80"/><SubstitutionsVisitor Player="M.Pollard" Position="TE" UniformNumber="81"/><SubstitutionsVisitor Player="B.Pyatt" Position="WR" UniformNumber="84"/><SubstitutionsVisitor Player="A.Moorehead" Position="WR" UniformNumber="85"/><SubstitutionsVisitor Player="T.Walters" Position="WR" UniformNumber="86"/><SubstitutionsVisitor Player="C.Bratzke" Position="DE" UniformNumber="92"/><SubstitutionsVisitor Player="J.Williams" Position="DT" UniformNumber="96"/><SubstitutionsVisitor Player="R.Mathis" Position="DE" UniformNumber="98"/><SubstitutionsVisitor Player="B.Scioli" Position="DE" UniformNumber="99"/><DidNotPlayVisitor Player="B.Huard" Position="QB" UniformNumber="7"/><NotActiveVisitor Player="J.Mungro" Position="RB" UniformNumber="23"/><NotActiveVisitor Player="J.Jefferson" Position="DB" UniformNumber="29"/><NotActiveVisitor Player="D.Strickland" Position="DB" UniformNumber="30"/><NotActiveVisitor Player="D.Rhodes" Position="RB" UniformNumber="33"/><NotActiveVisitor Player="A.Floyd" Position="DB" UniformNumber="39"/><NotActiveVisitor Player="C.June" Position="LB" UniformNumber="59"/><NotActiveVisitor Player="B.Hicks" Position="DT" UniformNumber="72"/><NotActiveVisitor Player="B.Stokley" Position="WR" UniformNumber="83"/><FieldGoalSummaryVisitor Player="M.Vanderjagt" FieldGoals="(22) (46) (45)"/><FieldGoalSummaryHome Player="P.Dawson" FieldGoals="(19) (20)"/><ScoringPlay Team="Browns" Quarter="1" Time="0:53" PlayDescription="P.Dawson 19 yd. Field Goal (12-76, 8:12)" VisitorScore="0" HomeScore="3"/><ScoringPlay Team="Colts" Quarter="2" Time="0:00" PlayDescription="M.Vanderjagt 22 yd. Field Goal (6-6, 0:29)" VisitorScore="3" HomeScore="3"/><ScoringPlay Team="Colts" Quarter="3" Time="3:43" PlayDescription="M.Vanderjagt 46 yd. Field Goal (11-52, 6:02)" VisitorScore="6" HomeScore="3"/><ScoringPlay Team="Browns" Quarter="4" Time="8:44" PlayDescription="P.Dawson 20 yd. Field Goal (18-86, 9:59)" VisitorScore="6" HomeScore="6"/><ScoringPlay Team="Colts" Quarter="4" Time="0:01" PlayDescription="M.Vanderjagt 45 yd. Field Goal (11-65, 2:38)" VisitorScore="9" HomeScore="6"/></GamebookSummary><IndividualStatistics><RusherVisitor Player="E.James" Attempts="15" Yards="67" Average="4.5" Touchdowns="0" Long="12" UniformNumber="32"/><RusherVisitor Player="Total" Attempts="15" Yards="67" Average="4.5" Touchdowns="0" Long="12"/><RusherHome Player="W.Green" Attempts="21" Yards="86" Average="4.1" Touchdowns="0" Long="15" UniformNumber="31"/><RusherHome Player="J.White" Attempts="2" Yards="7" Average="3.5" Touchdowns="0" Long="4" UniformNumber="30"/><RusherHome Player="J.Jackson" Attempts="2" Yards="6" Average="3.0" Touchdowns="0" Long="3" UniformNumber="29"/><RusherHome Player="D.Northcutt" Attempts="1" Yards="-1" Average="-1.0" Touchdowns="0" Long="-1" UniformNumber="86"/><RusherHome Player="Total" Attempts="26" Yards="98" Average="3.8" Touchdowns="0" Long="15"/><PasserVisitor Player="P.Manning" Attempts="43" Completions="27" Yards="211" Sacks="1" SackYardage="7" Touchdowns="0" Long="18" Interceptions="2" Rating="55.5" UniformNumber="18"/><PasserVisitor Player="Total" Attempts="43" Completions="27" Yards="211" Sacks="1" SackYardage="7" Touchdowns="0" Long="18" Interceptions="2" Rating="55.5"/><PasserHome Player="K.Holcomb" Attempts="29" Completions="20" Yards="182" Sacks="0" SackYardage="0" Touchdowns="0" Long="24" Interceptions="2" Rating="57.0" UniformNumber="10"/><PasserHome Player="Total" Attempts="29" Completions="20" Yards="182" Sacks="0" SackYardage="0" Touchdowns="0" Long="24" Interceptions="2" Rating="57.0"/><ReceiverVisitor Player="M.Harrison" Number="9" Yards="44" Average="4.9" Touchdowns="0" Long="11" UniformNumber="88"/><ReceiverVisitor Player="E.James" Number="5" Yards="29" Average="5.8" Touchdowns="0" Long="9" UniformNumber="32"/><ReceiverVisitor Player="R.Wayne" Number="3" Yards="39" Average="13.0" Touchdowns="0" Long="15" UniformNumber="87"/><ReceiverVisitor Player="M.Pollard" Number="3" Yards="28" Average="9.3" Touchdowns="0" Long="18" UniformNumber="81"/><ReceiverVisitor Player="T.Walters" Number="3" Yards="27" Average="9.0" Touchdowns="0" Long="10" UniformNumber="86"/><ReceiverVisitor Player="R.Williams" Number="2" Yards="19" Average="9.5" Touchdowns="0" Long="10" UniformNumber="35"/><ReceiverVisitor Player="D.Clark" Number="1" Yards="18" Average="18.0" Touchdowns="0" Long="18" UniformNumber="44"/><ReceiverVisitor Player="J.Davenport" Number="1" Yards="7" Average="7.0" Touchdowns="0" Long="7" UniformNumber="80"/><ReceiverVisitor Player="Total" Number="27" Yards="211" Average="7.8" Touchdowns="0" Long="18"/><ReceiverHome Player="D.Northcutt" Number="5" Yards="57" Average="11.4" Touchdowns="0" Long="24" UniformNumber="86"/><ReceiverHome Player="J.White" Number="4" Yards="19" Average="4.8" Touchdowns="0" Long="17" UniformNumber="30"/><ReceiverHome Player="K.Johnson" Number="3" Yards="26" Average="8.7" Touchdowns="0" Long="10" UniformNumber="85"/><ReceiverHome Player="W.Green" Number="3" Yards="19" Average="6.3" Touchdowns="0" Long="11" UniformNumber="31"/><ReceiverHome Player="S.Heiden" Number="2" Yards="22" Average="11.0" Touchdowns="0" Long="16" UniformNumber="82"/><ReceiverHome Player="A.Davis" Number="1" Yards="18" Average="18.0" Touchdowns="0" Long="18" UniformNumber="87"/><ReceiverHome Player="Q.Morgan" Number="1" Yards="14" Average="14.0" Touchdowns="0" Long="14" UniformNumber="81"/><ReceiverHome Player="A.Shea" Number="1" Yards="7" Average="7.0" Touchdowns="0" Long="7" UniformNumber="80"/><ReceiverHome Player="Total" Number="20" Yards="182" Average="9.1" Touchdowns="0" Long="24"/><InterceptorVisitor Player="N.Harper" Number="2" Yards="43" Average="21.5" Long="39" Touchdowns="0" UniformNumber="25"/><InterceptorVisitor Player="Total" Number="2" Yards="43" Average="21.5" Long="39" Touchdowns="0"/><InterceptorHome Player="K.Bentley" Number="1" Yards="25" Average="25.0" Long="25" Touchdowns="0" UniformNumber="59"/><InterceptorHome Player="B.Taylor" Number="1" Yards="0" Average="0.0" Long="0" Touchdowns="0" UniformNumber="58"/><InterceptorHome Player="Total" Number="2" Yards="25" Average="12.5" Long="25" Touchdowns="0"/><PunterVisitor Player="H.Smith" Number="3" Yards="119" Average="39.7" Touchbacks="0" Inside20="1" Long="50" NetPuntingAverage="39" UniformNumber="17"/><PunterVisitor Player="Total" Number="3" Yards="119" Average="39.7" Touchbacks="0" Inside20="1" Long="50" NetPuntingAverage="39"/><PunterHome Player="C.Gardocki" Number="3" Yards="127" Average="42.3" Touchbacks="1" Inside20="2" Long="49" NetPuntingAverage="35" UniformNumber="17"/><PunterHome Player="Total" Number="3" Yards="127" Average="42.3" Touchbacks="1" Inside20="2" Long="49" NetPuntingAverage="35"/><PuntReturnerVisitor Player="B.Pyatt" Number="1" Yards="2" Average="2.0" FairCatches="0" Long="2" Touchdowns="0" UniformNumber="84"/><PuntReturnerVisitor Player="[DOWNED]" Number="1" Yards="0" Average="0.0" FairCatches="0" Long="0" Touchdowns="0"/><PuntReturnerVisitor Player="[TOUCHBACK]" Number="1" Yards="0" Average="0.0" FairCatches="0" Long="0" Touchdowns="0"/><PuntReturnerVisitor Player="Returns" Number="1" Yards="2" Average="2.0" FairCatches="0" Long="2" Touchdowns="0"/><PuntReturnerHome Player="D.Northcutt" Number="1" Yards="2" Average="2.0" FairCatches="1" Long="2" Touchdowns="0" UniformNumber="86"/><PuntReturnerHome Player="[OUT OF BOUNDS]" Number="1" Yards="0" Average="0.0" FairCatches="0" Long="0" Touchdowns="0"/><PuntReturnerHome Player="Returns" Number="1" Yards="2" Average="2.0" FairCatches="1" Long="2" Touchdowns="0"/><KickOffReturnerVisitor Player="B.Pyatt" Number="2" Yards="49" Average="24.5" FairCatches="0" Long="35" Touchdowns="0" UniformNumber="84"/><KickOffReturnerVisitor Player="B.Allen" Number="1" Yards="6" Average="6.0" FairCatches="0" Long="6" Touchdowns="0" UniformNumber="43"/><KickOffReturnerVisitor Player="Returns" Number="3" Yards="55" Average="18.3" FairCatches="0" Long="35" Touchdowns="0"/><KickOffReturnerHome Player="Q.Morgan" Number="1" Yards="20" Average="20.0" FairCatches="0" Long="20" Touchdowns="0" UniformNumber="81"/><KickOffReturnerHome Player="A.King" Number="1" Yards="16" Average="16.0" FairCatches="0" Long="16" Touchdowns="0" UniformNumber="84"/><KickOffReturnerHome Player="J.White" Number="1" Yards="0" Average="0.0" FairCatches="0" Long="0" Touchdowns="0" UniformNumber="30"/><KickOffReturnerHome Player="Returns" Number="3" Yards="36" Average="12.0" FairCatches="0" Long="20" Touchdowns="0"/><FumblesVisitor Player="E.James" Fumbles="1" OwnRecoveries="0" Yards="0" Touchdowns="0" ForcedFumbles="0" OpponentRecoveries="0" OpponentYards="0" OpponentTouchdowns="0" OutOfBounds="1" Lost="0" UniformNumber="32"/><FumblesVisitor Player="M.Pollard" Fumbles="1" OwnRecoveries="0" Yards="0" Touchdowns="0" ForcedFumbles="0" OpponentRecoveries="0" OpponentYards="0" OpponentTouchdowns="0" OutOfBounds="1" Lost="0" UniformNumber="81"/><FumblesVisitor Player="W.Harris" Fumbles="0" OwnRecoveries="0" Yards="0" Touchdowns="0" ForcedFumbles="1" OpponentRecoveries="0" OpponentYards="0" OpponentTouchdowns="0" OutOfBounds="0" Lost="0" UniformNumber="21"/><FumblesVisitor Player="Total" Fumbles="2" OwnRecoveries="0" Yards="0" Touchdowns="0" ForcedFumbles="1" OpponentRecoveries="0" OpponentYards="0" OpponentTouchdowns="0" OutOfBounds="2" Lost="0"/><FumblesHome Player="D.Northcutt" Fumbles="1" OwnRecoveries="2" Yards="0" Touchdowns="0" ForcedFumbles="0" OpponentRecoveries="0" OpponentYards="0" OpponentTouchdowns="0" OutOfBounds="0" Lost="0" UniformNumber="86"/><FumblesHome Player="W.Green" Fumbles="1" OwnRecoveries="0" Yards="0" Touchdowns="0" ForcedFumbles="0" OpponentRecoveries="0" OpponentYards="0" OpponentTouchdowns="0" OutOfBounds="0" Lost="0" UniformNumber="31"/><FumblesHome Player="R.Griffith" Fumbles="0" OwnRecoveries="0" Yards="0" Touchdowns="0" ForcedFumbles="1" OpponentRecoveries="0" OpponentYards="0" OpponentTouchdowns="0" OutOfBounds="0" Lost="0" UniformNumber="24"/><FumblesHome Player="D.McCutcheon" Fumbles="0" OwnRecoveries="0" Yards="0" Touchdowns="0" ForcedFumbles="1" OpponentRecoveries="0" OpponentYards="0" OpponentTouchdowns="0" OutOfBounds="0" Lost="0" UniformNumber="33"/><FumblesHome Player="Total" Fumbles="2" OwnRecoveries="2" Yards="0" Touchdowns="0" ForcedFumbles="2" OpponentRecoveries="0" OpponentYards="0" OpponentTouchdowns="0" OutOfBounds="0" Lost="0"/></IndividualStatistics><TeamStatistics Description="TOTAL FIRST DOWNS" VisitorStats="18" HomeStats="18"/><TeamStatistics Description="By Rushing" VisitorStats="3" HomeStats="6"/><TeamStatistics Description="By Passing" VisitorStats="14" HomeStats="9"/><TeamStatistics Description="By Penalty" VisitorStats="1" HomeStats="3"/><TeamStatistics Description="THIRD DOWN EFFICIENCY" VisitorStats="7-12-58%" HomeStats="4-11-36%"/><TeamStatistics Description="FOURTH DOWN EFFICIENCY" VisitorStats="0-0-0%" HomeStats="0-0-0%"/><TeamStatistics Description="TOTAL NET YARDS" VisitorStats="271" HomeStats="280"/><TeamStatistics Description="Total Offensive Plays (inc. times thrown passing)" VisitorStats="59" HomeStats="55"/><TeamStatistics Description="Average gain per offensive play" VisitorStats="4.6" HomeStats="5.1"/><TeamStatistics Description="NET YARDS RUSHING" VisitorStats="67" HomeStats="98"/><TeamStatistics Description="Total Rushing Plays" VisitorStats="15" HomeStats="26"/><TeamStatistics Description="Average gain per rushing play" VisitorStats="4.5" HomeStats="3.8"/><TeamStatistics Description="Tackles for a loss-number and yards" VisitorStats="1-1" HomeStats="4-5"/><TeamStatistics Description="NET YARDS PASSING" VisitorStats="204" HomeStats="182"/><TeamStatistics Description="Times thrown - yards lost attempting to pass" VisitorStats="1-7" HomeStats="0-0"/><TeamStatistics Description="Gross yards passing" VisitorStats="211" HomeStats="182"/><TeamStatistics Description="PASS ATTEMPTS-COMPLETIONS-HAD INTERCEPTED" VisitorStats="43-27-2" HomeStats="29-20-2"/><TeamStatistics Description="Avg gain per pass play (inc.# thrown passing)" VisitorStats="4.6" HomeStats="6.3"/><TeamStatistics Description="KICKOFFS Number-In End Zone-Touchbacks" VisitorStats="3-0-0" HomeStats="3-0-0"/><TeamStatistics Description="PUNTS Number and Average" VisitorStats="3-39.7" HomeStats="3-42.3"/><TeamStatistics Description="Had Blocked" VisitorStats="0" HomeStats="0"/><TeamStatistics Description="FGs - PATs Had Blocked" VisitorStats="0-0" HomeStats="0-0"/><TeamStatistics Description="Net Punting Average" VisitorStats="39.0" HomeStats="35.0"/><TeamStatistics Description="TOTAL RETURN YARDAGE (Not Including Kickoffs)" VisitorStats="45" HomeStats="27"/><TeamStatistics Description="No. and Yards Punt Returns" VisitorStats="1-2" HomeStats="1-2"/><TeamStatistics Description="No. and Yards Kickoff Returns" VisitorStats="3-55" HomeStats="3-36"/><TeamStatistics Description="No. and Yards Interception Returns" VisitorStats="2-43" HomeStats="2-25"/><TeamStatistics Description="PENALTIES Number and Yards" VisitorStats="9-53" HomeStats="9-64"/><TeamStatistics Description="FUMBLES Number and Lost" VisitorStats="2-0" HomeStats="2-0"/><TeamStatistics Description="TOUCHDOWNS" VisitorStats="0" HomeStats="0"/><TeamStatistics Description="Rushing" VisitorStats="0" HomeStats="0"/><TeamStatistics Description="Passing" VisitorStats="0" HomeStats="0"/><TeamStatistics Description="EXTRA POINTS Made-Attempts" VisitorStats="0-0" HomeStats="0-0"/><TeamStatistics Description="Kicking Made-Attempts" VisitorStats="0-0" HomeStats="0-0"/><TeamStatistics Description="FIELD GOALS Made-Attempts" VisitorStats="3-3" HomeStats="2-2"/><TeamStatistics Description="GOAL TO GO EFFICIENCY" VisitorStats="0-2-0%" HomeStats="0-2-0%"/><TeamStatistics Description="RED ZONE EFFICIENCY" VisitorStats="0-2-0%" HomeStats="0-2-0%"/><TeamStatistics Description="SAFETIES" VisitorStats="0" HomeStats="0"/><TeamStatistics Description="FINAL SCORE" VisitorStats="9" HomeStats="6"/><TeamStatistics Description="TIME OF POSSESSION" VisitorStats="27:21" HomeStats="32:39"/><DriveChart AverageDriveStartVisitor="(256) Average IND 32" KickoffDriveInfoVisitor="Colts: 3 - IND 26" AverageDriveStartHome="(164) Average CLV 23" KickoffDriveInfoHome="Browns: 2 - CLV 18" TimeOfPossessionTotalVisitor="27:21" TimeOfPossessionTotalHome="32:39" TimeOfPossessionQ1Visitor="6:48" TimeOfPossessionQ1Home="8:12" TimeOfPossessionQ2Visitor="8:11" TimeOfPossessionQ2Home="6:49" TimeOfPossessionQ3Visitor="6:02" TimeOfPossessionQ3Home="8:58" TimeOfPossessionQ4Visitor="6:20" TimeOfPossessionQ4Home="8:40"><DriveVisitor Number="1" Quarter="1" TimeReceived="15:00" TimeLost="9:05" TimeOfPossession="5:55" HowBallObtained="Kickoff" DriveBegan="IND 38" PlayCount="12" YardsGained="60" YardsPenalized="0" NetYards="60" FirstDowns="4" LastScrimmage="*CLV 2" HowGivenUp="Interception"/><DriveVisitor Number="2" Quarter="2" TimeReceived="0:53" TimeLost="10:52" TimeOfPossession="5:01" HowBallObtained="Kickoff" DriveBegan="IND 15" PlayCount="8" YardsGained="44" YardsPenalized="0" NetYards="44" FirstDowns="3" LastScrimmage="CLV 41" HowGivenUp="Punt"/><DriveVisitor Number="3" Quarter="2" TimeReceived="6:01" TimeLost="2:38" TimeOfPossession="3:23" HowBallObtained="Punt" DriveBegan="IND 4" PlayCount="5" YardsGained="20" YardsPenalized="-5" NetYards="15" FirstDowns="1" LastScrimmage="IND 19" HowGivenUp="Punt"/><DriveVisitor Number="4" Quarter="2" TimeReceived="1:53" TimeLost="1:42" TimeOfPossession="0:11" HowBallObtained="Interception" DriveBegan="CLV 44" PlayCount="2" YardsGained="0" YardsPenalized="0" NetYards="0" FirstDowns="0" LastScrimmage="CLV 44" HowGivenUp="Interception"/><DriveVisitor Number="5" Quarter="2" TimeReceived="0:29" TimeLost="0:00" TimeOfPossession="0:29" HowBallObtained="Interception" DriveBegan="CLV 10" PlayCount="6" YardsGained="2" YardsPenalized="4" NetYards="6" FirstDowns="1" LastScrimmage="*CLV 4" HowGivenUp="Field Goal"/><DriveVisitor Number="6" Quarter="3" TimeReceived="9:45" TimeLost="3:43" TimeOfPossession="6:02" HowBallObtained="Punt" DriveBegan="IND 20" PlayCount="11" YardsGained="57" YardsPenalized="-5" NetYards="52" FirstDowns="3" LastScrimmage="CLV 28" HowGivenUp="Field Goal"/><DriveVisitor Number="7" Quarter="4" TimeReceived="8:44" TimeLost="5:02" TimeOfPossession="3:42" HowBallObtained="Kickoff" DriveBegan="IND 25" PlayCount="7" YardsGained="23" YardsPenalized="-10" NetYards="13" FirstDowns="1" LastScrimmage="IND 38" HowGivenUp="Punt"/><DriveVisitor Number="8" Quarter="4" TimeReceived="2:39" TimeLost="0:01" TimeOfPossession="2:38" HowBallObtained="Punt" DriveBegan="IND 8" PlayCount="11" YardsGained="65" YardsPenalized="0" NetYards="65" FirstDowns="5" LastScrimmage="CLV 27" HowGivenUp="Field Goal"/><DriveHome Number="1" Quarter="1" TimeReceived="9:05" TimeLost="0:53" TimeOfPossession="8:12" HowBallObtained="Interception" DriveBegan="CLV 23" PlayCount="12" YardsGained="61" YardsPenalized="15" NetYards="76" FirstDowns="5" LastScrimmage="*IND 1" HowGivenUp="Field Goal"/><DriveHome Number="2" Quarter="2" TimeReceived="10:52" TimeLost="6:01" TimeOfPossession="4:51" HowBallObtained="Punt" DriveBegan="CLV 7" PlayCount="9" YardsGained="56" YardsPenalized="-5" NetYards="51" FirstDowns="3" LastScrimmage="IND 42" HowGivenUp="Punt"/><DriveHome Number="3" Quarter="2" TimeReceived="2:38" TimeLost="1:53" TimeOfPossession="0:45" HowBallObtained="Punt" DriveBegan="CLV 33" PlayCount="2" YardsGained="2" YardsPenalized="-5" NetYards="-3" FirstDowns="0" LastScrimmage="CLV 30" HowGivenUp="Interception"/><DriveHome Number="4" Quarter="2" TimeReceived="1:42" TimeLost="0:29" TimeOfPossession="1:13" HowBallObtained="Interception" DriveBegan="CLV 37" PlayCount="4" YardsGained="13" YardsPenalized="-10" NetYards="3" FirstDowns="0" LastScrimmage="CLV 40" HowGivenUp="Interception"/><DriveHome Number="5" Quarter="3" TimeReceived="15:00" TimeLost="9:45" TimeOfPossession="5:15" HowBallObtained="Kickoff" DriveBegan="CLV 25" PlayCount="8" YardsGained="45" YardsPenalized="-10" NetYards="35" FirstDowns="2" LastScrimmage="IND 40" HowGivenUp="Punt"/><DriveHome Number="6" Quarter="4" TimeReceived="3:43" TimeLost="8:44" TimeOfPossession="9:59" HowBallObtained="Kickoff" DriveBegan="CLV 12" PlayCount="18" YardsGained="88" YardsPenalized="-2" NetYards="86" FirstDowns="7" LastScrimmage="*IND 2" HowGivenUp="Field Goal"/><DriveHome Number="7" Quarter="4" TimeReceived="5:02" TimeLost="2:39" TimeOfPossession="2:23" HowBallObtained="Punt" DriveBegan="CLV 27" PlayCount="4" YardsGained="18" YardsPenalized="0" NetYards="18" FirstDowns="1" LastScrimmage="CLV 45" HowGivenUp="Punt"/><DriveHome Number="8" Quarter="4" TimeReceived="0:01" TimeLost="0:00" TimeOfPossession="0:01" HowBallObtained="Kickoff" DriveBegan="" PlayCount="0" YardsGained="0" YardsPenalized="0" NetYards="0" FirstDowns="0" LastScrimmage="" HowGivenUp="End of Game"/></DriveChart><DefensiveStatistics><DefenderVisitor Player="M.Doss" Tackles="7" Assists="3" Combined="10" Sacks="0" SackYards="0" Interceptions="0" PassDefences="0" ForcedFumbles="0" FumbleRecoveries="0" SpecialTeamsTackles="0" SpecialTeamsAssists="0" SpecialTeamsForcedFumbles="0" SpecialTeamsFumbleRecoveries="0" SpecialTeamsBlocks="0" MiscellaneousTackles="0" MiscellaneousAssists="0" MiscellaneousForcedFumbles="0" MiscellaneousFumbleRecoveries="0" UniformNumber="20"/><DefenderVisitor Player="I.Bashir" Tackles="5" Assists="3" Combined="8" Sacks="0" SackYards="0" Interceptions="0" PassDefences="0" ForcedFumbles="0" FumbleRecoveries="0" SpecialTeamsTackles="0" SpecialTeamsAssists="0" SpecialTeamsForcedFumbles="0" SpecialTeamsFumbleRecoveries="0" SpecialTeamsBlocks="0" MiscellaneousTackles="0" MiscellaneousAssists="0" MiscellaneousForcedFumbles="0" MiscellaneousFumbleRecoveries="0" UniformNumber="28"/><DefenderVisitor Player="N.Harper" Tackles="6" Assists="0" Combined="6" Sacks="0" SackYards="0" Interceptions="2" PassDefences="4" ForcedFumbles="0" FumbleRecoveries="0" SpecialTeamsTackles="0" SpecialTeamsAssists="0" SpecialTeamsForcedFumbles="0" SpecialTeamsFumbleRecoveries="0" SpecialTeamsBlocks="0" MiscellaneousTackles="0" MiscellaneousAssists="0" MiscellaneousForcedFumbles="0" MiscellaneousFumbleRecoveries="0" UniformNumber="25"/><DefenderVisitor Player="W.Harris" Tackles="5" Assists="1" Combined="6" Sacks="0" SackYards="0" Interceptions="0" PassDefences="0" ForcedFumbles="1" FumbleRecoveries="0" SpecialTeamsTackles="0" SpecialTeamsAssists="0" SpecialTeamsForcedFumbles="0" SpecialTeamsFumbleRecoveries="0" SpecialTeamsBlocks="0" MiscellaneousTackles="0" MiscellaneousAssists="0" MiscellaneousForcedFumbles="0" MiscellaneousFumbleRecoveries="0" UniformNumber="21"/><DefenderVisitor Player="M.Washington" Tackles="2" Assists="4" Combined="6" Sacks="0" SackYards="0" Interceptions="0" PassDefences="1" ForcedFumbles="0" FumbleRecoveries="0" SpecialTeamsTackles="0" SpecialTeamsAssists="0" SpecialTeamsForcedFumbles="0" SpecialTeamsFumbleRecoveries="0" SpecialTeamsBlocks="0" MiscellaneousTackles="0" MiscellaneousAssists="0" MiscellaneousForcedFumbles="0" MiscellaneousFumbleRecoveries="0" UniformNumber="53"/><DefenderVisitor Player="R.Morris" Tackles="4" Assists="1" Combined="5" Sacks="0" SackYards="0" Interceptions="0" PassDefences="0" ForcedFumbles="0" FumbleRecoveries="0" SpecialTeamsTackles="0" SpecialTeamsAssists="0" SpecialTeamsForcedFumbles="0" SpecialTeamsFumbleRecoveries="0" SpecialTeamsBlocks="0" MiscellaneousTackles="0" MiscellaneousAssists="0" MiscellaneousForcedFumbles="0" MiscellaneousFumbleRecoveries="0" UniformNumber="94"/><DefenderVisitor Player="J.Nelson" Tackles="4" Assists="0" Combined="4" Sacks="0" SackYards="0" Interceptions="0" PassDefences="0" ForcedFumbles="0" FumbleRecoveries="0" SpecialTeamsTackles="0" SpecialTeamsAssists="0" SpecialTeamsForcedFumbles="0" SpecialTeamsFumbleRecoveries="0" SpecialTeamsBlocks="0" MiscellaneousTackles="0" MiscellaneousAssists="0" MiscellaneousForcedFumbles="0" MiscellaneousFumbleRecoveries="0" UniformNumber="57"/><DefenderVisitor Player="D.Thornton" Tackles="2" Assists="2" Combined="4" Sacks="0" SackYards="0" Interceptions="0" PassDefences="0" ForcedFumbles="0" FumbleRecoveries="0" SpecialTeamsTackles="0" SpecialTeamsAssists="0" SpecialTeamsForcedFumbles="0" SpecialTeamsFumbleRecoveries="0" SpecialTeamsBlocks="0" MiscellaneousTackles="0" MiscellaneousAssists="0" MiscellaneousForcedFumbles="0" MiscellaneousFumbleRecoveries="0" UniformNumber="50"/><DefenderVisitor Player="B.Scioli" Tackles="2" Assists="0" Combined="2" Sacks="0" SackYards="0" Interceptions="0" PassDefences="0" ForcedFumbles="0" FumbleRecoveries="0" SpecialTeamsTackles="0" SpecialTeamsAssists="0" SpecialTeamsForcedFumbles="0" SpecialTeamsFumbleRecoveries="0" SpecialTeamsBlocks="0" MiscellaneousTackles="0" MiscellaneousAssists="0" MiscellaneousForcedFumbles="0" MiscellaneousFumbleRecoveries="0" UniformNumber="99"/><DefenderVisitor Player="D.Macklin" Tackles="2" Assists="0" Combined="2" Sacks="0" SackYards="0" Interceptions="0" PassDefences="0" ForcedFumbles="0" FumbleRecoveries="0" SpecialTeamsTackles="0" SpecialTeamsAssists="0" SpecialTeamsForcedFumbles="0" SpecialTeamsFumbleRecoveries="0" SpecialTeamsBlocks="0" MiscellaneousTackles="0" MiscellaneousAssists="0" MiscellaneousForcedFumbles="0" MiscellaneousFumbleRecoveries="0" UniformNumber="27"/><DefenderVisitor Player="M.Reagor" Tackles="1" Assists="1" Combined="2" Sacks="0" SackYards="0" Interceptions="0" PassDefences="0" ForcedFumbles="0" FumbleRecoveries="0" SpecialTeamsTackles="0" SpecialTeamsAssists="0" SpecialTeamsForcedFumbles="0" SpecialTeamsFumbleRecoveries="0" SpecialTeamsBlocks="0" MiscellaneousTackles="0" MiscellaneousAssists="0" MiscellaneousForcedFumbles="0" MiscellaneousFumbleRecoveries="0" UniformNumber="90"/><DefenderVisitor Player="L.Tripplett" Tackles="1" Assists="1" Combined="2" Sacks="0" SackYards="0" Interceptions="0" PassDefences="0" ForcedFumbles="0" FumbleRecoveries="0" SpecialTeamsTackles="0" SpecialTeamsAssists="0" SpecialTeamsForcedFumbles="0" SpecialTeamsFumbleRecoveries="0" SpecialTeamsBlocks="0" MiscellaneousTackles="0" MiscellaneousAssists="0" MiscellaneousForcedFumbles="0" MiscellaneousFumbleRecoveries="0" UniformNumber="75"/><DefenderVisitor Player="R.Brock" Tackles="0" Assists="2" Combined="2" Sacks="0" SackYards="0" Interceptions="0" PassDefences="0" ForcedFumbles="0" FumbleRecoveries="0" SpecialTeamsTackles="0" SpecialTeamsAssists="0" SpecialTeamsForcedFumbles="0" SpecialTeamsFumbleRecoveries="0" SpecialTeamsBlocks="0" MiscellaneousTackles="0" MiscellaneousAssists="0" MiscellaneousForcedFumbles="0" MiscellaneousFumbleRecoveries="0" UniformNumber="79"/><DefenderVisitor Player="C.Bratzke" Tackles="1" Assists="0" Combined="1" Sacks="0" SackYards="0" Interceptions="0" PassDefences="0" ForcedFumbles="0" FumbleRecoveries="0" SpecialTeamsTackles="0" SpecialTeamsAssists="0" SpecialTeamsForcedFumbles="0" SpecialTeamsFumbleRecoveries="0" SpecialTeamsBlocks="0" MiscellaneousTackles="0" MiscellaneousAssists="0" MiscellaneousForcedFumbles="0" MiscellaneousFumbleRecoveries="0" UniformNumber="92"/><DefenderVisitor Player="TEAM" Tackles="1" Assists="0" Combined="1" Sacks="0" SackYards="0" Interceptions="0" PassDefences="0" ForcedFumbles="0" FumbleRecoveries="0" SpecialTeamsTackles="0" SpecialTeamsAssists="0" SpecialTeamsForcedFumbles="0" SpecialTeamsFumbleRecoveries="0" SpecialTeamsBlocks="0" MiscellaneousTackles="0" MiscellaneousAssists="0" MiscellaneousForcedFumbles="0" MiscellaneousFumbleRecoveries="0" UniformNumber="TT"/><DefenderVisitor Player="R.Mathis" Tackles="1" Assists="0" Combined="1" Sacks="0" SackYards="0" Interceptions="0" PassDefences="0" ForcedFumbles="0" FumbleRecoveries="0" SpecialTeamsTackles="0" SpecialTeamsAssists="0" SpecialTeamsForcedFumbles="0" SpecialTeamsFumbleRecoveries="0" SpecialTeamsBlocks="0" MiscellaneousTackles="0" MiscellaneousAssists="0" MiscellaneousForcedFumbles="0" MiscellaneousFumbleRecoveries="0" UniformNumber="98"/><DefenderVisitor Player="D.Freeney" Tackles="1" Assists="0" Combined="1" Sacks="0" SackYards="0" Interceptions="0" PassDefences="0" ForcedFumbles="0" FumbleRecoveries="0" SpecialTeamsTackles="0" SpecialTeamsAssists="0" SpecialTeamsForcedFumbles="0" SpecialTeamsFumbleRecoveries="0" SpecialTeamsBlocks="0" MiscellaneousTackles="0" MiscellaneousAssists="0" MiscellaneousForcedFumbles="0" MiscellaneousFumbleRecoveries="0" UniformNumber="93"/><DefenderVisitor Player="J.Williams" Tackles="1" Assists="0" Combined="1" Sacks="0" SackYards="0" Interceptions="0" PassDefences="0" ForcedFumbles="0" FumbleRecoveries="0" SpecialTeamsTackles="0" SpecialTeamsAssists="0" SpecialTeamsForcedFumbles="0" SpecialTeamsFumbleRecoveries="0" SpecialTeamsBlocks="0" MiscellaneousTackles="0" MiscellaneousAssists="0" MiscellaneousForcedFumbles="0" MiscellaneousFumbleRecoveries="0" UniformNumber="96"/><DefenderVisitor Player="C.Crosby" Tackles="0" Assists="0" Combined="0" Sacks="0" SackYards="0" Interceptions="0" PassDefences="0" ForcedFumbles="0" FumbleRecoveries="0" SpecialTeamsTackles="2" SpecialTeamsAssists="0" SpecialTeamsForcedFumbles="0" SpecialTeamsFumbleRecoveries="0" SpecialTeamsBlocks="0" MiscellaneousTackles="0" MiscellaneousAssists="0" MiscellaneousForcedFumbles="0" MiscellaneousFumbleRecoveries="0" UniformNumber="31"/><DefenderVisitor Player="G.Brackett" Tackles="0" Assists="0" Combined="0" Sacks="0" SackYards="0" Interceptions="0" PassDefences="0" ForcedFumbles="0" FumbleRecoveries="0" SpecialTeamsTackles="2" SpecialTeamsAssists="0" SpecialTeamsForcedFumbles="0" SpecialTeamsFumbleRecoveries="0" SpecialTeamsBlocks="0" MiscellaneousTackles="0" MiscellaneousAssists="0" MiscellaneousForcedFumbles="0" MiscellaneousFumbleRecoveries="0" UniformNumber="58"/><DefenderVisitor Player="R.DeMulling" Tackles="0" Assists="0" Combined="0" Sacks="0" SackYards="0" Interceptions="0" PassDefences="0" ForcedFumbles="0" FumbleRecoveries="0" SpecialTeamsTackles="0" SpecialTeamsAssists="0" SpecialTeamsForcedFumbles="0" SpecialTeamsFumbleRecoveries="0" SpecialTeamsBlocks="0" MiscellaneousTackles="1" MiscellaneousAssists="0" MiscellaneousForcedFumbles="0" MiscellaneousFumbleRecoveries="0" UniformNumber="64"/><DefenderVisitor Player="E.James" Tackles="0" Assists="0" Combined="0" Sacks="0" SackYards="0" Interceptions="0" PassDefences="0" ForcedFumbles="0" FumbleRecoveries="0" SpecialTeamsTackles="0" SpecialTeamsAssists="0" SpecialTeamsForcedFumbles="0" SpecialTeamsFumbleRecoveries="0" SpecialTeamsBlocks="0" MiscellaneousTackles="1" MiscellaneousAssists="0" MiscellaneousForcedFumbles="0" MiscellaneousFumbleRecoveries="0" UniformNumber="32"/><DefenderVisitor Player="Total" Tackles="46" Assists="18" Combined="64" Sacks="0" SackYards="0" Interceptions="2" PassDefences="5" ForcedFumbles="1" FumbleRecoveries="0" SpecialTeamsTackles="4" SpecialTeamsAssists="0" SpecialTeamsForcedFumbles="0" SpecialTeamsFumbleRecoveries="0" SpecialTeamsBlocks="0" MiscellaneousTackles="2" MiscellaneousAssists="0" MiscellaneousForcedFumbles="0" MiscellaneousFumbleRecoveries="0"/><DefenderHome Player="B.Taylor" Tackles="6" Assists="5" Combined="11" Sacks="0" SackYards="0" Interceptions="1" PassDefences="1" ForcedFumbles="0" FumbleRecoveries="0" SpecialTeamsTackles="0" SpecialTeamsAssists="0" SpecialTeamsForcedFumbles="0" SpecialTeamsFumbleRecoveries="0" SpecialTeamsBlocks="0" MiscellaneousTackles="0" MiscellaneousAssists="0" MiscellaneousForcedFumbles="0" MiscellaneousFumbleRecoveries="0" UniformNumber="58"/><DefenderHome Player="D.McCutcheon" Tackles="9" Assists="0" Combined="9" Sacks="0" SackYards="0" Interceptions="0" PassDefences="1" ForcedFumbles="1" FumbleRecoveries="0" SpecialTeamsTackles="0" SpecialTeamsAssists="0" SpecialTeamsForcedFumbles="0" SpecialTeamsFumbleRecoveries="0" SpecialTeamsBlocks="0" MiscellaneousTackles="0" MiscellaneousAssists="0" MiscellaneousForcedFumbles="0" MiscellaneousFumbleRecoveries="0" UniformNumber="33"/><DefenderHome Player="A.Davis" Tackles="8" Assists="0" Combined="8" Sacks="0" SackYards="0" Interceptions="0" PassDefences="0" ForcedFumbles="0" FumbleRecoveries="0" SpecialTeamsTackles="0" SpecialTeamsAssists="0" SpecialTeamsForcedFumbles="0" SpecialTeamsFumbleRecoveries="0" SpecialTeamsBlocks="0" MiscellaneousTackles="0" MiscellaneousAssists="0" MiscellaneousForcedFumbles="0" MiscellaneousFumbleRecoveries="0" UniformNumber="54"/><DefenderHome Player="R.Griffith" Tackles="6" Assists="0" Combined="6" Sacks="0" SackYards="0" Interceptions="0" PassDefences="0" ForcedFumbles="1" FumbleRecoveries="0" SpecialTeamsTackles="0" SpecialTeamsAssists="0" SpecialTeamsForcedFumbles="0" SpecialTeamsFumbleRecoveries="0" SpecialTeamsBlocks="0" MiscellaneousTackles="0" MiscellaneousAssists="0" MiscellaneousForcedFumbles="0" MiscellaneousFumbleRecoveries="0" UniformNumber="24"/><DefenderHome Player="A.Henry" Tackles="3" Assists="0" Combined="3" Sacks="0" SackYards="0" Interceptions="0" PassDefences="1" ForcedFumbles="0" FumbleRecoveries="0" SpecialTeamsTackles="0" SpecialTeamsAssists="0" SpecialTeamsForcedFumbles="0" SpecialTeamsFumbleRecoveries="0" SpecialTeamsBlocks="0" MiscellaneousTackles="0" MiscellaneousAssists="0" MiscellaneousForcedFumbles="0" MiscellaneousFumbleRecoveries="0" UniformNumber="37"/><DefenderHome Player="K.Bentley" Tackles="1" Assists="2" Combined="3" Sacks="0" SackYards="0" Interceptions="1" PassDefences="1" ForcedFumbles="0" FumbleRecoveries="0" SpecialTeamsTackles="0" SpecialTeamsAssists="0" SpecialTeamsForcedFumbles="0" SpecialTeamsFumbleRecoveries="0" SpecialTeamsBlocks="0" MiscellaneousTackles="0" MiscellaneousAssists="0" MiscellaneousForcedFumbles="0" MiscellaneousFumbleRecoveries="0" UniformNumber="59"/><DefenderHome Player="O.Roye" Tackles="2" Assists="0" Combined="2" Sacks="0" SackYards="0" Interceptions="0" PassDefences="1" ForcedFumbles="0" FumbleRecoveries="0" SpecialTeamsTackles="0" SpecialTeamsAssists="0" SpecialTeamsForcedFumbles="0" SpecialTeamsFumbleRecoveries="0" SpecialTeamsBlocks="0" MiscellaneousTackles="0" MiscellaneousAssists="0" MiscellaneousForcedFumbles="0" MiscellaneousFumbleRecoveries="0" UniformNumber="99"/><DefenderHome Player="C.Crocker" Tackles="2" Assists="0" Combined="2" Sacks="0" SackYards="0" Interceptions="0" PassDefences="0" ForcedFumbles="0" FumbleRecoveries="0" SpecialTeamsTackles="0" SpecialTeamsAssists="0" SpecialTeamsForcedFumbles="0" SpecialTeamsFumbleRecoveries="0" SpecialTeamsBlocks="0" MiscellaneousTackles="0" MiscellaneousAssists="0" MiscellaneousForcedFumbles="0" MiscellaneousFumbleRecoveries="0" UniformNumber="25"/><DefenderHome Player="G.Warren" Tackles="2" Assists="0" Combined="2" Sacks="0" SackYards="0" Interceptions="0" PassDefences="0" ForcedFumbles="0" FumbleRecoveries="0" SpecialTeamsTackles="0" SpecialTeamsAssists="0" SpecialTeamsForcedFumbles="0" SpecialTeamsFumbleRecoveries="0" SpecialTeamsBlocks="0" MiscellaneousTackles="0" MiscellaneousAssists="0" MiscellaneousForcedFumbles="0" MiscellaneousFumbleRecoveries="0" UniformNumber="94"/><DefenderHome Player="C.Brown" Tackles="2" Assists="0" Combined="2" Sacks="1" SackYards="7" Interceptions="0" PassDefences="0" ForcedFumbles="0" FumbleRecoveries="0" SpecialTeamsTackles="0" SpecialTeamsAssists="0" SpecialTeamsForcedFumbles="0" SpecialTeamsFumbleRecoveries="0" SpecialTeamsBlocks="0" MiscellaneousTackles="0" MiscellaneousAssists="0" MiscellaneousForcedFumbles="0" MiscellaneousFumbleRecoveries="0" UniformNumber="92"/><DefenderHome Player="E.Little" Tackles="1" Assists="1" Combined="2" Sacks="0" SackYards="0" Interceptions="0" PassDefences="0" ForcedFumbles="0" FumbleRecoveries="0" SpecialTeamsTackles="0" SpecialTeamsAssists="0" SpecialTeamsForcedFumbles="0" SpecialTeamsFumbleRecoveries="0" SpecialTeamsBlocks="0" MiscellaneousTackles="0" MiscellaneousAssists="0" MiscellaneousForcedFumbles="0" MiscellaneousFumbleRecoveries="0" UniformNumber="20"/><DefenderHome Player="K.Lang" Tackles="1" Assists="0" Combined="1" Sacks="0" SackYards="0" Interceptions="0" PassDefences="0" ForcedFumbles="0" FumbleRecoveries="0" SpecialTeamsTackles="0" SpecialTeamsAssists="0" SpecialTeamsForcedFumbles="0" SpecialTeamsFumbleRecoveries="0" SpecialTeamsBlocks="0" MiscellaneousTackles="0" MiscellaneousAssists="0" MiscellaneousForcedFumbles="0" MiscellaneousFumbleRecoveries="0" UniformNumber="96"/><DefenderHome Player="M.Word" Tackles="0" Assists="0" Combined="0" Sacks="0" SackYards="0" Interceptions="0" PassDefences="1" ForcedFumbles="0" FumbleRecoveries="0" SpecialTeamsTackles="0" SpecialTeamsAssists="0" SpecialTeamsForcedFumbles="0" SpecialTeamsFumbleRecoveries="0" SpecialTeamsBlocks="0" MiscellaneousTackles="0" MiscellaneousAssists="0" MiscellaneousForcedFumbles="0" MiscellaneousFumbleRecoveries="0" UniformNumber="90"/><DefenderHome Player="C.Thompson" Tackles="0" Assists="0" Combined="0" Sacks="0" SackYards="0" Interceptions="0" PassDefences="0" ForcedFumbles="0" FumbleRecoveries="0" SpecialTeamsTackles="1" SpecialTeamsAssists="1" SpecialTeamsForcedFumbles="0" SpecialTeamsFumbleRecoveries="0" SpecialTeamsBlocks="0" MiscellaneousTackles="0" MiscellaneousAssists="0" MiscellaneousForcedFumbles="0" MiscellaneousFumbleRecoveries="0" UniformNumber="51"/><DefenderHome Player="L.Bodden" Tackles="0" Assists="0" Combined="0" Sacks="0" SackYards="0" Interceptions="0" PassDefences="0" ForcedFumbles="0" FumbleRecoveries="0" SpecialTeamsTackles="1" SpecialTeamsAssists="0" SpecialTeamsForcedFumbles="0" SpecialTeamsFumbleRecoveries="0" SpecialTeamsBlocks="0" MiscellaneousTackles="0" MiscellaneousAssists="0" MiscellaneousForcedFumbles="0" MiscellaneousFumbleRecoveries="0" UniformNumber="28"/><DefenderHome Player="L.Sanders" Tackles="0" Assists="0" Combined="0" Sacks="0" SackYards="0" Interceptions="0" PassDefences="0" ForcedFumbles="0" FumbleRecoveries="0" SpecialTeamsTackles="1" SpecialTeamsAssists="0" SpecialTeamsForcedFumbles="0" SpecialTeamsFumbleRecoveries="0" SpecialTeamsBlocks="0" MiscellaneousTackles="0" MiscellaneousAssists="0" MiscellaneousForcedFumbles="0" MiscellaneousFumbleRecoveries="0" UniformNumber="21"/><DefenderHome Player="B.Boyer" Tackles="0" Assists="0" Combined="0" Sacks="0" SackYards="0" Interceptions="0" PassDefences="0" ForcedFumbles="0" FumbleRecoveries="0" SpecialTeamsTackles="1" SpecialTeamsAssists="0" SpecialTeamsForcedFumbles="0" SpecialTeamsFumbleRecoveries="0" SpecialTeamsBlocks="0" MiscellaneousTackles="0" MiscellaneousAssists="0" MiscellaneousForcedFumbles="0" MiscellaneousFumbleRecoveries="0" UniformNumber="52"/><DefenderHome Player="M.Jameson" Tackles="0" Assists="0" Combined="0" Sacks="0" SackYards="0" Interceptions="0" PassDefences="0" ForcedFumbles="0" FumbleRecoveries="0" SpecialTeamsTackles="0" SpecialTeamsAssists="1" SpecialTeamsForcedFumbles="0" SpecialTeamsFumbleRecoveries="0" SpecialTeamsBlocks="0" MiscellaneousTackles="0" MiscellaneousAssists="0" MiscellaneousForcedFumbles="0" MiscellaneousFumbleRecoveries="0" UniformNumber="22"/><DefenderHome Player="S.Coates" Tackles="0" Assists="0" Combined="0" Sacks="0" SackYards="0" Interceptions="0" PassDefences="0" ForcedFumbles="0" FumbleRecoveries="0" SpecialTeamsTackles="0" SpecialTeamsAssists="1" SpecialTeamsForcedFumbles="0" SpecialTeamsFumbleRecoveries="0" SpecialTeamsBlocks="0" MiscellaneousTackles="0" MiscellaneousAssists="0" MiscellaneousForcedFumbles="0" MiscellaneousFumbleRecoveries="0" UniformNumber="56"/><DefenderHome Player="D.Northcutt" Tackles="0" Assists="0" Combined="0" Sacks="0" SackYards="0" Interceptions="0" PassDefences="0" ForcedFumbles="0" FumbleRecoveries="0" SpecialTeamsTackles="0" SpecialTeamsAssists="0" SpecialTeamsForcedFumbles="0" SpecialTeamsFumbleRecoveries="1" SpecialTeamsBlocks="0" MiscellaneousTackles="1" MiscellaneousAssists="0" MiscellaneousForcedFumbles="0" MiscellaneousFumbleRecoveries="1" UniformNumber="86"/><DefenderHome Player="J.Faine" Tackles="0" Assists="0" Combined="0" Sacks="0" SackYards="0" Interceptions="0" PassDefences="0" ForcedFumbles="0" FumbleRecoveries="0" SpecialTeamsTackles="0" SpecialTeamsAssists="0" SpecialTeamsForcedFumbles="0" SpecialTeamsFumbleRecoveries="0" SpecialTeamsBlocks="0" MiscellaneousTackles="1" MiscellaneousAssists="0" MiscellaneousForcedFumbles="0" MiscellaneousFumbleRecoveries="0" UniformNumber="50"/><DefenderHome Player="Total" Tackles="43" Assists="8" Combined="51" Sacks="1" SackYards="7" Interceptions="2" PassDefences="6" ForcedFumbles="2" FumbleRecoveries="0" SpecialTeamsTackles="4" SpecialTeamsAssists="3" SpecialTeamsForcedFumbles="0" SpecialTeamsFumbleRecoveries="1" SpecialTeamsBlocks="0" MiscellaneousTackles="2" MiscellaneousAssists="0" MiscellaneousForcedFumbles="0" MiscellaneousFumbleRecoveries="1"/></DefensiveStatistics><FirstHalfSummary Title="First Half Summary" PeriodScoresVisitor="0  3 = 3" PeriodScoresHome="3  0 = 3" TimeOfPossessionVisitor="14:59" TimeOfPossessionHome="15:01"><ScoringPlay Team="Browns" Quarter="1" Time="0:53" PlayDescription="P.Dawson 19 yd. Field Goal (12-76, 8:12)" VisitorScore="0" HomeScore="3"/><ScoringPlay Team="Colts" Quarter="2" Time="0:00" PlayDescription="M.Vanderjagt 22 yd. Field Goal (6-6, 0:29)" VisitorScore="3" HomeScore="3"/><TeamStatistics Description="TOTAL FIRST DOWNS" VisitorStats="9" HomeStats="8"/><TeamStatistics Description="First Downs Rushing-Passing-by Penalty" VisitorStats="2 - 6 - 1" HomeStats="1 - 5 - 2"/><TeamStatistics Description="THIRD DOWN EFFICIENCY" VisitorStats="3-6-50%" HomeStats="0-4-0%"/><TeamStatistics Description="TOTAL NET YARDS" VisitorStats="126" HomeStats="132"/><TeamStatistics Description="Total Offensive Plays" VisitorStats="32" HomeStats="26"/><TeamStatistics Description="NET YARDS RUSHING" VisitorStats="35" HomeStats="28"/><TeamStatistics Description="NET YARDS PASSING" VisitorStats="91" HomeStats="104"/><TeamStatistics Description="Gross Yards Passing" VisitorStats="98" HomeStats="104"/><TeamStatistics Description="Times thrown-yards lost attempting to pass" VisitorStats="1-7" HomeStats="0-0"/><TeamStatistics Description="Pass Attempts-Completions-Had Intercepted" VisitorStats="23 - 13 - 2" HomeStats="14 - 9 - 2"/><TeamStatistics Description="Punts-Number and Average" VisitorStats="2 - 42" HomeStats="1 - 38"/><TeamStatistics Description="Penalties-Number and Yards" VisitorStats="5 - 30" HomeStats="5 - 34"/><TeamStatistics Description="Fumbles-Number and Lost" VisitorStats="2 - 0" HomeStats="1 - 0"/><TeamStatistics Description="Red Zone Efficiency" VisitorStats="0-2-0%" HomeStats="0-2-0%"/><TeamStatistics Description="Average Drive Start" VisitorStats="IND 32" HomeStats="CLV 23"/><RusherVisitor Player="E.James" Attempts="8" Yards="35" Average="4.4" Touchdowns="0" Long="12" UniformNumber="32"/><RusherVisitor Player="Total" Attempts="8" Yards="35" Average="4.4" Touchdowns="0" Long="12"/><RusherHome Player="W.Green" Attempts="8" Yards="19" Average="2.4" Touchdowns="0" Long="5" UniformNumber="31"/><RusherHome Player="J.Jackson" Attempts="2" Yards="6" Average="3.0" Touchdowns="0" Long="3" UniformNumber="29"/><RusherHome Player="J.White" Attempts="1" Yards="4" Average="4.0" Touchdowns="0" Long="4" UniformNumber="30"/><RusherHome Player="D.Northcutt" Attempts="1" Yards="-1" Average="-1.0" Touchdowns="0" Long="-1" UniformNumber="86"/><RusherHome Player="Total" Attempts="12" Yards="28" Average="2.3" Touchdowns="0" Long="5"/><PasserVisitor Player="P.Manning" Attempts="23" Completions="13" Yards="98" Sacks="1" SackYardage="7" Touchdowns="0" Long="18" Interceptions="2" Rating="30.7" UniformNumber="18"/><PasserVisitor Player="Total" Attempts="23" Completions="13" Yards="98" Sacks="1" SackYardage="7" Touchdowns="0" Long="18" Interceptions="2" Rating="30.7"/><PasserHome Player="K.Holcomb" Attempts="14" Completions="9" Yards="104" Sacks="0" SackYardage="0" Touchdowns="0" Long="24" Interceptions="2" Rating="47.0" UniformNumber="10"/><PasserHome Player="Total" Attempts="14" Completions="9" Yards="104" Sacks="0" SackYardage="0" Touchdowns="0" Long="24" Interceptions="2" Rating="47.0"/><ReceiverVisitor Player="M.Harrison" Number="4" Yards="18" Average="4.5" Touchdowns="0" Long="8" UniformNumber="88"/><ReceiverVisitor Player="M.Pollard" Number="3" Yards="28" Average="9.3" Touchdowns="0" Long="18" UniformNumber="81"/><ReceiverVisitor Player="E.James" Number="2" Yards="13" Average="6.5" Touchdowns="0" Long="7" UniformNumber="32"/><ReceiverVisitor Player="R.Wayne" Number="1" Yards="13" Average="13.0" Touchdowns="0" Long="13" UniformNumber="87"/><ReceiverVisitor Player="T.Walters" Number="1" Yards="10" Average="10.0" Touchdowns="0" Long="10" UniformNumber="86"/><ReceiverVisitor Player="R.Williams" Number="1" Yards="9" Average="9.0" Touchdowns="0" Long="9" UniformNumber="35"/><ReceiverVisitor Player="J.Davenport" Number="1" Yards="7" Average="7.0" Touchdowns="0" Long="7" UniformNumber="80"/><ReceiverVisitor Player="Total" Number="13" Yards="98" Average="7.5" Touchdowns="0" Long="18"/><ReceiverHome Player="D.Northcutt" Number="3" Yards="50" Average="16.7" Touchdowns="0" Long="24" UniformNumber="86"/><ReceiverHome Player="W.Green" Number="2" Yards="13" Average="6.5" Touchdowns="0" Long="11" UniformNumber="31"/><ReceiverHome Player="S.Heiden" Number="1" Yards="16" Average="16.0" Touchdowns="0" Long="16" UniformNumber="82"/><ReceiverHome Player="Q.Morgan" Number="1" Yards="14" Average="14.0" Touchdowns="0" Long="14" UniformNumber="81"/><ReceiverHome Player="K.Johnson" Number="1" Yards="6" Average="6.0" Touchdowns="0" Long="6" UniformNumber="85"/><ReceiverHome Player="J.White" Number="1" Yards="5" Average="5.0" Touchdowns="0" Long="5" UniformNumber="30"/><ReceiverHome Player="Total" Number="9" Yards="104" Average="11.6" Touchdowns="0" Long="24"/><DefenderVisitor Player="I.Bashir" Tackles="3" Assists="2" Combined="5" Sacks="0" SackYards="0" Interceptions="0" PassDefences="0" ForcedFumbles="0" FumbleRecoveries="0" SpecialTeamsTackles="0" SpecialTeamsAssists="0" SpecialTeamsForcedFumbles="0" SpecialTeamsFumbleRecoveries="0" SpecialTeamsBlocks="0" MiscellaneousTackles="0" MiscellaneousAssists="0" MiscellaneousForcedFumbles="0" MiscellaneousFumbleRecoveries="0" UniformNumber="28"/><DefenderVisitor Player="M.Washington" Tackles="2" Assists="2" Combined="4" Sacks="0" SackYards="0" Interceptions="0" PassDefences="1" ForcedFumbles="0" FumbleRecoveries="0" SpecialTeamsTackles="0" SpecialTeamsAssists="0" SpecialTeamsForcedFumbles="0" SpecialTeamsFumbleRecoveries="0" SpecialTeamsBlocks="0" MiscellaneousTackles="0" MiscellaneousAssists="0" MiscellaneousForcedFumbles="0" MiscellaneousFumbleRecoveries="0" UniformNumber="53"/><DefenderVisitor Player="R.Morris" Tackles="3" Assists="0" Combined="3" Sacks="0" SackYards="0" Interceptions="0" PassDefences="0" ForcedFumbles="0" FumbleRecoveries="0" SpecialTeamsTackles="0" SpecialTeamsAssists="0" SpecialTeamsForcedFumbles="0" SpecialTeamsFumbleRecoveries="0" SpecialTeamsBlocks="0" MiscellaneousTackles="0" MiscellaneousAssists="0" MiscellaneousForcedFumbles="0" MiscellaneousFumbleRecoveries="0" UniformNumber="94"/><DefenderVisitor Player="M.Doss" Tackles="2" Assists="1" Combined="3" Sacks="0" SackYards="0" Interceptions="0" PassDefences="0" ForcedFumbles="0" FumbleRecoveries="0" SpecialTeamsTackles="0" SpecialTeamsAssists="0" SpecialTeamsForcedFumbles="0" SpecialTeamsFumbleRecoveries="0" SpecialTeamsBlocks="0" MiscellaneousTackles="0" MiscellaneousAssists="0" MiscellaneousForcedFumbles="0" MiscellaneousFumbleRecoveries="0" UniformNumber="20"/><DefenderVisitor Player="D.Thornton" Tackles="1" Assists="2" Combined="3" Sacks="0" SackYards="0" Interceptions="0" PassDefences="0" ForcedFumbles="0" FumbleRecoveries="0" SpecialTeamsTackles="0" SpecialTeamsAssists="0" SpecialTeamsForcedFumbles="0" SpecialTeamsFumbleRecoveries="0" SpecialTeamsBlocks="0" MiscellaneousTackles="0" MiscellaneousAssists="0" MiscellaneousForcedFumbles="0" MiscellaneousFumbleRecoveries="0" UniformNumber="50"/><DefenderVisitor Player="B.Scioli" Tackles="2" Assists="0" Combined="2" Sacks="0" SackYards="0" Interceptions="0" PassDefences="0" ForcedFumbles="0" FumbleRecoveries="0" SpecialTeamsTackles="0" SpecialTeamsAssists="0" SpecialTeamsForcedFumbles="0" SpecialTeamsFumbleRecoveries="0" SpecialTeamsBlocks="0" MiscellaneousTackles="0" MiscellaneousAssists="0" MiscellaneousForcedFumbles="0" MiscellaneousFumbleRecoveries="0" UniformNumber="99"/><DefenderVisitor Player="C.Bratzke" Tackles="1" Assists="0" Combined="1" Sacks="0" SackYards="0" Interceptions="0" PassDefences="0" ForcedFumbles="0" FumbleRecoveries="0" SpecialTeamsTackles="0" SpecialTeamsAssists="0" SpecialTeamsForcedFumbles="0" SpecialTeamsFumbleRecoveries="0" SpecialTeamsBlocks="0" MiscellaneousTackles="0" MiscellaneousAssists="0" MiscellaneousForcedFumbles="0" MiscellaneousFumbleRecoveries="0" UniformNumber="92"/><DefenderVisitor Player="N.Harper" Tackles="1" Assists="0" Combined="1" Sacks="0" SackYards="0" Interceptions="2" PassDefences="3" ForcedFumbles="0" FumbleRecoveries="0" SpecialTeamsTackles="0" SpecialTeamsAssists="0" SpecialTeamsForcedFumbles="0" SpecialTeamsFumbleRecoveries="0" SpecialTeamsBlocks="0" MiscellaneousTackles="0" MiscellaneousAssists="0" MiscellaneousForcedFumbles="0" MiscellaneousFumbleRecoveries="0" UniformNumber="25"/><DefenderVisitor Player="W.Harris" Tackles="1" Assists="0" Combined="1" Sacks="0" SackYards="0" Interceptions="0" PassDefences="0" ForcedFumbles="0" FumbleRecoveries="0" SpecialTeamsTackles="0" SpecialTeamsAssists="0" SpecialTeamsForcedFumbles="0" SpecialTeamsFumbleRecoveries="0" SpecialTeamsBlocks="0" MiscellaneousTackles="0" MiscellaneousAssists="0" MiscellaneousForcedFumbles="0" MiscellaneousFumbleRecoveries="0" UniformNumber="21"/><DefenderVisitor Player="D.Macklin" Tackles="1" Assists="0" Combined="1" Sacks="0" SackYards="0" Interceptions="0" PassDefences="0" ForcedFumbles="0" FumbleRecoveries="0" SpecialTeamsTackles="0" SpecialTeamsAssists="0" SpecialTeamsForcedFumbles="0" SpecialTeamsFumbleRecoveries="0" SpecialTeamsBlocks="0" MiscellaneousTackles="0" MiscellaneousAssists="0" MiscellaneousForcedFumbles="0" MiscellaneousFumbleRecoveries="0" UniformNumber="27"/><DefenderVisitor Player="R.Mathis" Tackles="1" Assists="0" Combined="1" Sacks="0" SackYards="0" Interceptions="0" PassDefences="0" ForcedFumbles="0" FumbleRecoveries="0" SpecialTeamsTackles="0" SpecialTeamsAssists="0" SpecialTeamsForcedFumbles="0" SpecialTeamsFumbleRecoveries="0" SpecialTeamsBlocks="0" MiscellaneousTackles="0" MiscellaneousAssists="0" MiscellaneousForcedFumbles="0" MiscellaneousFumbleRecoveries="0" UniformNumber="98"/><DefenderVisitor Player="J.Nelson" Tackles="1" Assists="0" Combined="1" Sacks="0" SackYards="0" Interceptions="0" PassDefences="0" ForcedFumbles="0" FumbleRecoveries="0" SpecialTeamsTackles="0" SpecialTeamsAssists="0" SpecialTeamsForcedFumbles="0" SpecialTeamsFumbleRecoveries="0" SpecialTeamsBlocks="0" MiscellaneousTackles="0" MiscellaneousAssists="0" MiscellaneousForcedFumbles="0" MiscellaneousFumbleRecoveries="0" UniformNumber="57"/><DefenderVisitor Player="M.Reagor" Tackles="1" Assists="0" Combined="1" Sacks="0" SackYards="0" Interceptions="0" PassDefences="0" ForcedFumbles="0" FumbleRecoveries="0" SpecialTeamsTackles="0" SpecialTeamsAssists="0" SpecialTeamsForcedFumbles="0" SpecialTeamsFumbleRecoveries="0" SpecialTeamsBlocks="0" MiscellaneousTackles="0" MiscellaneousAssists="0" MiscellaneousForcedFumbles="0" MiscellaneousFumbleRecoveries="0" UniformNumber="90"/><DefenderVisitor Player="R.Brock" Tackles="0" Assists="1" Combined="1" Sacks="0" SackYards="0" Interceptions="0" PassDefences="0" ForcedFumbles="0" FumbleRecoveries="0" SpecialTeamsTackles="0" SpecialTeamsAssists="0" SpecialTeamsForcedFumbles="0" SpecialTeamsFumbleRecoveries="0" SpecialTeamsBlocks="0" MiscellaneousTackles="0" MiscellaneousAssists="0" MiscellaneousForcedFumbles="0" MiscellaneousFumbleRecoveries="0" UniformNumber="79"/><DefenderVisitor Player="C.Crosby" Tackles="0" Assists="0" Combined="0" Sacks="0" SackYards="0" Interceptions="0" PassDefences="0" ForcedFumbles="0" FumbleRecoveries="0" SpecialTeamsTackles="1" SpecialTeamsAssists="0" SpecialTeamsForcedFumbles="0" SpecialTeamsFumbleRecoveries="0" SpecialTeamsBlocks="0" MiscellaneousTackles="0" MiscellaneousAssists="0" MiscellaneousForcedFumbles="0" MiscellaneousFumbleRecoveries="0" UniformNumber="31"/><DefenderVisitor Player="R.DeMulling" Tackles="0" Assists="0" Combined="0" Sacks="0" SackYards="0" Interceptions="0" PassDefences="0" ForcedFumbles="0" FumbleRecoveries="0" SpecialTeamsTackles="0" SpecialTeamsAssists="0" SpecialTeamsForcedFumbles="0" SpecialTeamsFumbleRecoveries="0" SpecialTeamsBlocks="0" MiscellaneousTackles="1" MiscellaneousAssists="0" MiscellaneousForcedFumbles="0" MiscellaneousFumbleRecoveries="0" UniformNumber="64"/><DefenderVisitor Player="E.James" Tackles="0" Assists="0" Combined="0" Sacks="0" SackYards="0" Interceptions="0" PassDefences="0" ForcedFumbles="0" FumbleRecoveries="0" SpecialTeamsTackles="0" SpecialTeamsAssists="0" SpecialTeamsForcedFumbles="0" SpecialTeamsFumbleRecoveries="0" SpecialTeamsBlocks="0" MiscellaneousTackles="1" MiscellaneousAssists="0" MiscellaneousForcedFumbles="0" MiscellaneousFumbleRecoveries="0" UniformNumber="32"/><DefenderVisitor Player="TEAM" Tackles="1" Assists="0" Combined="1" Sacks="0" SackYards="0" Interceptions="0" PassDefences="0" ForcedFumbles="0" FumbleRecoveries="0" SpecialTeamsTackles="0" SpecialTeamsAssists="0" SpecialTeamsForcedFumbles="0" SpecialTeamsFumbleRecoveries="0" SpecialTeamsBlocks="0" MiscellaneousTackles="0" MiscellaneousAssists="0" MiscellaneousForcedFumbles="0" MiscellaneousFumbleRecoveries="0" UniformNumber="TT"/><DefenderVisitor Player="Total" Tackles="21" Assists="8" Combined="29" Sacks="0" SackYards="0" Interceptions="2" PassDefences="4" ForcedFumbles="0" FumbleRecoveries="0" SpecialTeamsTackles="1" SpecialTeamsAssists="0" SpecialTeamsForcedFumbles="0" SpecialTeamsFumbleRecoveries="0" SpecialTeamsBlocks="0" MiscellaneousTackles="2" MiscellaneousAssists="0" MiscellaneousForcedFumbles="0" MiscellaneousFumbleRecoveries="0"/><DefenderHome Player="B.Taylor" Tackles="3" Assists="5" Combined="8" Sacks="0" SackYards="0" Interceptions="1" PassDefences="1" ForcedFumbles="0" FumbleRecoveries="0" SpecialTeamsTackles="0" SpecialTeamsAssists="0" SpecialTeamsForcedFumbles="0" SpecialTeamsFumbleRecoveries="0" SpecialTeamsBlocks="0" MiscellaneousTackles="0" MiscellaneousAssists="0" MiscellaneousForcedFumbles="0" MiscellaneousFumbleRecoveries="0" UniformNumber="58"/><DefenderHome Player="D.McCutcheon" Tackles="5" Assists="0" Combined="5" Sacks="0" SackYards="0" Interceptions="0" PassDefences="1" ForcedFumbles="1" FumbleRecoveries="0" SpecialTeamsTackles="0" SpecialTeamsAssists="0" SpecialTeamsForcedFumbles="0" SpecialTeamsFumbleRecoveries="0" SpecialTeamsBlocks="0" MiscellaneousTackles="0" MiscellaneousAssists="0" MiscellaneousForcedFumbles="0" MiscellaneousFumbleRecoveries="0" UniformNumber="33"/><DefenderHome Player="R.Griffith" Tackles="4" Assists="0" Combined="4" Sacks="0" SackYards="0" Interceptions="0" PassDefences="0" ForcedFumbles="1" FumbleRecoveries="0" SpecialTeamsTackles="0" SpecialTeamsAssists="0" SpecialTeamsForcedFumbles="0" SpecialTeamsFumbleRecoveries="0" SpecialTeamsBlocks="0" MiscellaneousTackles="0" MiscellaneousAssists="0" MiscellaneousForcedFumbles="0" MiscellaneousFumbleRecoveries="0" UniformNumber="24"/><DefenderHome Player="A.Davis" Tackles="3" Assists="0" Combined="3" Sacks="0" SackYards="0" Interceptions="0" PassDefences="0" ForcedFumbles="0" FumbleRecoveries="0" SpecialTeamsTackles="0" SpecialTeamsAssists="0" SpecialTeamsForcedFumbles="0" SpecialTeamsFumbleRecoveries="0" SpecialTeamsBlocks="0" MiscellaneousTackles="0" MiscellaneousAssists="0" MiscellaneousForcedFumbles="0" MiscellaneousFumbleRecoveries="0" UniformNumber="54"/><DefenderHome Player="A.Henry" Tackles="2" Assists="0" Combined="2" Sacks="0" SackYards="0" Interceptions="0" PassDefences="1" ForcedFumbles="0" FumbleRecoveries="0" SpecialTeamsTackles="0" SpecialTeamsAssists="0" SpecialTeamsForcedFumbles="0" SpecialTeamsFumbleRecoveries="0" SpecialTeamsBlocks="0" MiscellaneousTackles="0" MiscellaneousAssists="0" MiscellaneousForcedFumbles="0" MiscellaneousFumbleRecoveries="0" UniformNumber="37"/><DefenderHome Player="G.Warren" Tackles="2" Assists="0" Combined="2" Sacks="0" SackYards="0" Interceptions="0" PassDefences="0" ForcedFumbles="0" FumbleRecoveries="0" SpecialTeamsTackles="0" SpecialTeamsAssists="0" SpecialTeamsForcedFumbles="0" SpecialTeamsFumbleRecoveries="0" SpecialTeamsBlocks="0" MiscellaneousTackles="0" MiscellaneousAssists="0" MiscellaneousForcedFumbles="0" MiscellaneousFumbleRecoveries="0" UniformNumber="94"/><DefenderHome Player="K.Bentley" Tackles="1" Assists="1" Combined="2" Sacks="0" SackYards="0" Interceptions="1" PassDefences="1" ForcedFumbles="0" FumbleRecoveries="0" SpecialTeamsTackles="0" SpecialTeamsAssists="0" SpecialTeamsForcedFumbles="0" SpecialTeamsFumbleRecoveries="0" SpecialTeamsBlocks="0" MiscellaneousTackles="0" MiscellaneousAssists="0" MiscellaneousForcedFumbles="0" MiscellaneousFumbleRecoveries="0" UniformNumber="59"/><DefenderHome Player="C.Brown" Tackles="1" Assists="0" Combined="1" Sacks="1" SackYards="7" Interceptions="0" PassDefences="0" ForcedFumbles="0" FumbleRecoveries="0" SpecialTeamsTackles="0" SpecialTeamsAssists="0" SpecialTeamsForcedFumbles="0" SpecialTeamsFumbleRecoveries="0" SpecialTeamsBlocks="0" MiscellaneousTackles="0" MiscellaneousAssists="0" MiscellaneousForcedFumbles="0" MiscellaneousFumbleRecoveries="0" UniformNumber="92"/><DefenderHome Player="C.Crocker" Tackles="1" Assists="0" Combined="1" Sacks="0" SackYards="0" Interceptions="0" PassDefences="0" ForcedFumbles="0" FumbleRecoveries="0" SpecialTeamsTackles="0" SpecialTeamsAssists="0" SpecialTeamsForcedFumbles="0" SpecialTeamsFumbleRecoveries="0" SpecialTeamsBlocks="0" MiscellaneousTackles="0" MiscellaneousAssists="0" MiscellaneousForcedFumbles="0" MiscellaneousFumbleRecoveries="0" UniformNumber="25"/><DefenderHome Player="E.Little" Tackles="0" Assists="1" Combined="1" Sacks="0" SackYards="0" Interceptions="0" PassDefences="0" ForcedFumbles="0" FumbleRecoveries="0" SpecialTeamsTackles="0" SpecialTeamsAssists="0" SpecialTeamsForcedFumbles="0" SpecialTeamsFumbleRecoveries="0" SpecialTeamsBlocks="0" MiscellaneousTackles="0" MiscellaneousAssists="0" MiscellaneousForcedFumbles="0" MiscellaneousFumbleRecoveries="0" UniformNumber="20"/><DefenderHome Player="L.Bodden" Tackles="0" Assists="0" Combined="0" Sacks="0" SackYards="0" Interceptions="0" PassDefences="0" ForcedFumbles="0" FumbleRecoveries="0" SpecialTeamsTackles="1" SpecialTeamsAssists="0" SpecialTeamsForcedFumbles="0" SpecialTeamsFumbleRecoveries="0" SpecialTeamsBlocks="0" MiscellaneousTackles="0" MiscellaneousAssists="0" MiscellaneousForcedFumbles="0" MiscellaneousFumbleRecoveries="0" UniformNumber="28"/><DefenderHome Player="J.Faine" Tackles="0" Assists="0" Combined="0" Sacks="0" SackYards="0" Interceptions="0" PassDefences="0" ForcedFumbles="0" FumbleRecoveries="0" SpecialTeamsTackles="0" SpecialTeamsAssists="0" SpecialTeamsForcedFumbles="0" SpecialTeamsFumbleRecoveries="0" SpecialTeamsBlocks="0" MiscellaneousTackles="1" MiscellaneousAssists="0" MiscellaneousForcedFumbles="0" MiscellaneousFumbleRecoveries="0" UniformNumber="50"/><DefenderHome Player="M.Jameson" Tackles="0" Assists="0" Combined="0" Sacks="0" SackYards="0" Interceptions="0" PassDefences="0" ForcedFumbles="0" FumbleRecoveries="0" SpecialTeamsTackles="0" SpecialTeamsAssists="1" SpecialTeamsForcedFumbles="0" SpecialTeamsFumbleRecoveries="0" SpecialTeamsBlocks="0" MiscellaneousTackles="0" MiscellaneousAssists="0" MiscellaneousForcedFumbles="0" MiscellaneousFumbleRecoveries="0" UniformNumber="22"/><DefenderHome Player="D.Northcutt" Tackles="0" Assists="0" Combined="0" Sacks="0" SackYards="0" Interceptions="0" PassDefences="0" ForcedFumbles="0" FumbleRecoveries="0" SpecialTeamsTackles="0" SpecialTeamsAssists="0" SpecialTeamsForcedFumbles="0" SpecialTeamsFumbleRecoveries="1" SpecialTeamsBlocks="0" MiscellaneousTackles="1" MiscellaneousAssists="0" MiscellaneousForcedFumbles="0" MiscellaneousFumbleRecoveries="0" UniformNumber="86"/><DefenderHome Player="O.Roye" Tackles="0" Assists="0" Combined="0" Sacks="0" SackYards="0" Interceptions="0" PassDefences="1" ForcedFumbles="0" FumbleRecoveries="0" SpecialTeamsTackles="0" SpecialTeamsAssists="0" SpecialTeamsForcedFumbles="0" SpecialTeamsFumbleRecoveries="0" SpecialTeamsBlocks="0" MiscellaneousTackles="0" MiscellaneousAssists="0" MiscellaneousForcedFumbles="0" MiscellaneousFumbleRecoveries="0" UniformNumber="99"/><DefenderHome Player="C.Thompson" Tackles="0" Assists="0" Combined="0" Sacks="0" SackYards="0" Interceptions="0" PassDefences="0" ForcedFumbles="0" FumbleRecoveries="0" SpecialTeamsTackles="1" SpecialTeamsAssists="1" SpecialTeamsForcedFumbles="0" SpecialTeamsFumbleRecoveries="0" SpecialTeamsBlocks="0" MiscellaneousTackles="0" MiscellaneousAssists="0" MiscellaneousForcedFumbles="0" MiscellaneousFumbleRecoveries="0" UniformNumber="51"/><DefenderHome Player="Total" Tackles="22" Assists="7" Combined="29" Sacks="1" SackYards="7" Interceptions="2" PassDefences="5" ForcedFumbles="2" FumbleRecoveries="0" SpecialTeamsTackles="2" SpecialTeamsAssists="2" SpecialTeamsForcedFumbles="0" SpecialTeamsFumbleRecoveries="1" SpecialTeamsBlocks="0" MiscellaneousTackles="2" MiscellaneousAssists="0" MiscellaneousForcedFumbles="0" MiscellaneousFumbleRecoveries="0"/></FirstHalfSummary><PlayByPlay><_1stQuarter><Play Header="IND wins toss, elects to Receive, and CLV elects to defend the West goal."/><Play Header="4-P.Dawson kicks 67 yards from CLV 30 to IND 3. 84-B.Pyatt to IND 38 for 35 yards (51-C.Thompson, 22-M.Jameson)."/><Play Header="Indianapolis Colts at 15:00, (1st play from scrimmage 14:52)"/><Play DownDistanceYardline="1-10-IND 38" EarnedFirstDown="False" PlayDescription="(14:52) 18-P.Manning pass to 35-R.Williams to IND 47 for 9 yards (37-A.Henry, 58-B.Taylor)."/><Play DownDistanceYardline="2-1-IND 47" EarnedFirstDown="False" PlayDescription="(14:24) 32-E.James right guard to IND 47 for no gain (24-R.Griffith)."/><Play PlayDescription="Timeout #1 by IND at 13:37."/><Play DownDistanceYardline="3-1-IND 47" EarnedFirstDown="False" PlayDescription="(13:37) 18-P.Manning pass to 81-M.Pollard to CLV 32 for 21 yards (33-D.McCutcheon). FUMBLES (33-D.McCutcheon), ball out of bounds at CLV 35. Browns player McCutheon injured on the play" FirstDownType="P1"/><Play DownDistanceYardline="1-10-CLV 35" EarnedFirstDown="True" PlayDescription="(13:27) (Shotgun) 18-P.Manning pass incomplete to 32-E.James."/><Play DownDistanceYardline="2-10-CLV 35" EarnedFirstDown="False" PlayDescription="(13:23) 32-E.James left guard to CLV 35 for no gain (24-R.Griffith)."/><Play DownDistanceYardline="3-10-CLV 35" EarnedFirstDown="False" PlayDescription="(12:45) (Shotgun) 18-P.Manning pass to 87-R.Wayne to CLV 22 for 13 yards (25-C.Crocker)." FirstDownType="P2"/><Play DownDistanceYardline="1-10-CLV 22" EarnedFirstDown="True" PlayDescription="(12:01) 32-E.James right tackle to CLV 19 for 3 yards (24-R.Griffith)."/><Play DownDistanceYardline="2-7-CLV 19" EarnedFirstDown="False" PlayDescription="(11:27) 18-P.Manning pass to 32-E.James to CLV 12 for 7 yards (58-B.Taylor)." FirstDownType="P3"/><Play DownDistanceYardline="1-10-CLV 12" EarnedFirstDown="True" PlayDescription="(10:46) 18-P.Manning pass incomplete to 32-E.James."/><Play DownDistanceYardline="2-10-CLV 12" EarnedFirstDown="False" PlayDescription="(10:41) 18-P.Manning pass to 32-E.James to CLV 6 for 6 yards (33-D.McCutcheon)."/><Play DownDistanceYardline="3-4-CLV 6" EarnedFirstDown="False" PlayDescription="(9:56) (Shotgun) 18-P.Manning pass to 88-M.Harrison to CLV 2 for 4 yards (54-A.Davis, 20-E.Little)." FirstDownType="P4"/><Play DownDistanceYardline="1-2-CLV 2" EarnedFirstDown="True" PlayDescription="(9:17) 18-P.Manning pass intended for 81-M.Pollard INTERCEPTED by 59-K.Bentley at CLV -2. 59-K.Bentley to CLV 23 for 25 yards (64-R.DeMulling)."/><Play Header="Cleveland Browns at 9:05"/><Play DownDistanceYardline="1-10-CLV 23" EarnedFirstDown="False" PlayDescription="(9:05) 10-K.Holcomb pass to 31-W.Green to IND 48 for 29 yards (20-M.Doss)."/><Play PlayDescription="PENALTY on CLV-72-R.Tucker, Offensive Holding, 10 yards, enforced at CLV 23 - No Play."/><Play DownDistanceYardline="1-20-CLV 13" EarnedFirstDown="False" PlayDescription="(8:39) PENALTY on IND-90-M.Reagor, Neutral Zone Infraction, 5 yards, enforced at CLV 13 - No Play."/><Play DownDistanceYardline="1-15-CLV 18" EarnedFirstDown="False" PlayDescription="(8:22) 31-W.Green right guard to CLV 23 for 5 yards (53-M.Washington, 28-I.Bashir)."/><Play DownDistanceYardline="2-10-CLV 23" EarnedFirstDown="False" PlayDescription="(7:45) 10-K.Holcomb pass to 81-Q.Morgan to CLV 37 for 14 yards (21-W.Harris)." FirstDownType="P1"/><Play DownDistanceYardline="1-10-CLV 37" EarnedFirstDown="True" PlayDescription="(7:08) 10-K.Holcomb pass to 30-J.White to CLV 43 for 6 yards (94-R.Morris)."/><Play PlayDescription="PENALTY on IND-21-W.Harris, Defensive Holding, 5 yards, enforced at CLV 37 - No Play." FirstDownType="X2"/><Play DownDistanceYardline="1-10-CLV 42" EarnedFirstDown="True" PlayDescription="(6:40) 31-W.Green right guard to CLV 46 for 4 yards (92-C.Bratzke, 50-D.Thornton)."/><Play DownDistanceYardline="2-6-CLV 46" EarnedFirstDown="False" PlayDescription="(6:03) 10-K.Holcomb pass to 86-D.Northcutt to IND 30 for 24 yards (28-I.Bashir, 20-M.Doss)." FirstDownType="P3"/><Play DownDistanceYardline="1-10-IND 30" EarnedFirstDown="True" PlayDescription="(5:20) 31-W.Green right guard to IND 26 for 4 yards (57-J.Nelson, 50-D.Thornton)."/><Play DownDistanceYardline="2-6-IND 26" EarnedFirstDown="False" PlayDescription="(4:44) 31-W.Green left end to IND 27 for -1 yards (20-M.Doss)."/><Play DownDistanceYardline="3-7-IND 27" EarnedFirstDown="False" PlayDescription="(4:03) (Shotgun) 10-K.Holcomb pass to 85-K.Johnson to IND 21 for 6 yards (25-N.Harper)."/><Play PlayDescription="PENALTY on IND-98-R.Mathis, Roughing the Passer, 10 yards, enforced at IND 21." FirstDownType="X4"/><Play DownDistanceYardline="1-10-IND 11" EarnedFirstDown="True" PlayDescription="(3:31) PENALTY on IND-92-C.Bratzke, Neutral Zone Infraction, 5 yards, enforced at IND 11 - No Play."/><Play DownDistanceYardline="1-5-IND 6" EarnedFirstDown="False" PlayDescription="(3:09) 31-W.Green right guard to IND 1 for 5 yards (Team)." FirstDownType="R5"/><Play DownDistanceYardline="1-1-IND 1" EarnedFirstDown="True" PlayDescription="(2:25) 31-W.Green right guard to IND 1 for no gain (53-M.Washington, 79-R.Brock)."/><Play DownDistanceYardline="2-1-IND 1" EarnedFirstDown="False" PlayDescription="(1:44) 10-K.Holcomb pass incomplete to 82-S.Heiden (53-M.Washington)."/><Play DownDistanceYardline="3-1-IND 1" EarnedFirstDown="False" PlayDescription="(1:38) 31-W.Green right end to IND 1 for no gain (50-D.Thornton, 53-M.Washington)."/><Play DownDistanceYardline="4-1-IND 1" EarnedFirstDown="False" PlayDescription="(:56) 4-P.Dawson 19 yard field goal is GOOD, Center-64-R.Pontbriand, Holder-17-C.Gardocki."/><Play Header="IND 0 CLV 3,  12 plays, 76 yards, 4 penalties,  8:12 drive, 14:07 elapsed"/><Play Header="4-P.Dawson kicks 69 yards from CLV 30 to IND 1. 84-B.Pyatt to IND 15 for 14 yards (28-L.Bodden, 51-C.Thompson)."/><Play Header="Indianapolis Colts at 0:53, (1st play from scrimmage 0:47)"/><Play DownDistanceYardline="1-10-IND 15" EarnedFirstDown="False" PlayDescription="(:47) 32-E.James right end to IND 27 for 12 yards (24-R.Griffith). FUMBLES (24-R.Griffith), ball out of bounds at IND 27. Browns player #24 caused fumble" FirstDownType="R5"/><Play DownDistanceYardline="1-10-IND 27" EarnedFirstDown="True" PlayDescription="(:22) 18-P.Manning pass to 81-M.Pollard to IND 33 for 6 yards (58-B.Taylor)."/><QuarterSummary Team="Indianapolis Colts" Score="0" TimeOfPossession="6:48" FirstDownsRushing="1" FirstDownsPassing="4" FirstDownsPenalty="0" FirstDownsTotal="5" ThirdDownEfficiency="3/3" FourthDownEfficiency="0/0"/><QuarterSummary Team="Cleveland Browns" Score="3" TimeOfPossession="8:12" FirstDownsRushing="1" FirstDownsPassing="2" FirstDownsPenalty="2" FirstDownsTotal="5" ThirdDownEfficiency="0/2" FourthDownEfficiency="0/0"/></_1stQuarter><_2ndQuarter><Play Header="Indianapolis Colts continued."/><Play DownDistanceYardline="2-4-IND 33" EarnedFirstDown="False" PlayDescription="(15:00) 18-P.Manning pass to 81-M.Pollard to IND 37 for 4 yards (33-D.McCutcheon, 58-B.Taylor)." FirstDownType="P6"/><Play DownDistanceYardline="1-10-IND 37" EarnedFirstDown="True" PlayDescription="(14:15) 18-P.Manning pass to 88-M.Harrison to IND 41 for 4 yards (33-D.McCutcheon, 58-B.Taylor)."/><Play DownDistanceYardline="2-6-IND 41" EarnedFirstDown="False" PlayDescription="(13:35) 32-E.James left tackle to CLV 48 for 11 yards (94-G.Warren)." FirstDownType="R7"/><Play DownDistanceYardline="1-10-CLV 48" EarnedFirstDown="True" PlayDescription="(12:46) 32-E.James left end to CLV 44 for 4 yards (37-A.Henry)."/><Play DownDistanceYardline="2-6-CLV 44" EarnedFirstDown="False" PlayDescription="(12:15) 18-P.Manning sacked at IND 49 for -7 yards (92-C.Brown)."/><Play DownDistanceYardline="3-13-IND 49" EarnedFirstDown="False" PlayDescription="(11:43) (Shotgun) 18-P.Manning pass to 86-T.Walters to CLV 41 for 10 yards (33-D.McCutcheon)."/><Play DownDistanceYardline="4-3-CLV 41" EarnedFirstDown="False" PlayDescription="(11:00) 17-H.Smith punts 34 yards to CLV 7, Center-48-J.Snow, fair catch by 86-D.Northcutt."/><Play Header="Cleveland Browns at 10:52"/><Play DownDistanceYardline="1-10-CLV 7" EarnedFirstDown="False" PlayDescription="(10:52) 31-W.Green right end to CLV 14 for 7 yards (20-M.Doss)."/><Play PlayDescription="PENALTY on CLV-85-K.Johnson, Offensive Holding, 5 yards, enforced at CLV 9."/><Play DownDistanceYardline="1-13-CLV 4" EarnedFirstDown="False" PlayDescription="(10:30) 10-K.Holcomb pass incomplete to 85-K.Johnson."/><Play DownDistanceYardline="2-13-CLV 4" EarnedFirstDown="False" PlayDescription="(10:24) 10-K.Holcomb pass to 86-D.Northcutt to CLV 26 for 22 yards (94-R.Morris, 28-I.Bashir)." FirstDownType="P6"/><Play DownDistanceYardline="1-10-CLV 26" EarnedFirstDown="True" PlayDescription="(9:47) 86-D.Northcutt right end to CLV 25 for -1 yards (94-R.Morris)."/><Play DownDistanceYardline="2-11-CLV 25" EarnedFirstDown="False" PlayDescription="(9:03) 10-K.Holcomb pass to 82-S.Heiden to CLV 41 for 16 yards (28-I.Bashir)." FirstDownType="P7"/><Play DownDistanceYardline="1-10-CLV 41" EarnedFirstDown="True" PlayDescription="(8:24) 10-K.Holcomb pass to 31-W.Green to IND 48 for 11 yards (94-R.Morris)." FirstDownType="P8"/><Play DownDistanceYardline="1-10-IND 48" EarnedFirstDown="True" PlayDescription="(7:35) 29-J.Jackson left guard to IND 45 for 3 yards (99-B.Scioli)."/><Play DownDistanceYardline="2-7-IND 45" EarnedFirstDown="False" PlayDescription="(6:58) 29-J.Jackson left tackle to IND 42 for 3 yards (99-B.Scioli)."/><Play DownDistanceYardline="3-4-IND 42" EarnedFirstDown="False" PlayDescription="(6:17) (Shotgun) 10-K.Holcomb pass incomplete to 86-D.Northcutt (25-N.Harper)."/><Play DownDistanceYardline="4-4-IND 42" EarnedFirstDown="False" PlayDescription="(6:11) 17-C.Gardocki punts 38 yards to IND 4, Center-64-R.Pontbriand, downed by CLV-82-S.Heiden."/><Play Header="Indianapolis Colts at 6:01"/><Play DownDistanceYardline="1-10-IND 4" EarnedFirstDown="False" PlayDescription="(6:01) 32-E.James right tackle to IND 9 for 5 yards (59-K.Bentley)."/><Play DownDistanceYardline="2-5-IND 9" EarnedFirstDown="False" PlayDescription="(5:25) 18-P.Manning pass to 80-J.Davenport to IND 16 for 7 yards (94-G.Warren, 58-B.Taylor)." FirstDownType="P8"/><Play DownDistanceYardline="1-10-IND 16" EarnedFirstDown="True" PlayDescription="(4:42) 32-E.James left end to IND 16 for no gain (54-A.Davis, 58-B.Taylor)."/><Play DownDistanceYardline="2-10-IND 16" EarnedFirstDown="False" PlayDescription="(4:03) 18-P.Manning pass to 88-M.Harrison to IND 24 for 8 yards (58-B.Taylor, 59-K.Bentley)."/><Play DownDistanceYardline="3-2-IND 24" EarnedFirstDown="False" PlayDescription="(3:20) (Shotgun) PENALTY on IND-78-T.Glenn, False Start, 5 yards, enforced at IND 24 - No Play."/><Play DownDistanceYardline="3-7-IND 19" EarnedFirstDown="False" PlayDescription="(2:53) (Shotgun) 18-P.Manning pass incomplete to 87-R.Wayne (37-A.Henry)."/><Play DownDistanceYardline="4-7-IND 19" EarnedFirstDown="False" PlayDescription="(2:48) 17-H.Smith punts 50 yards to CLV 31, Center-48-J.Snow. 86-D.Northcutt MUFFS catch, and recovers at CLV 31. 86-D.Northcutt to CLV 33 for 2 yards (31-C.Crosby)."/><Play Header="Cleveland Browns at 2:38"/><Play DownDistanceYardline="1-10-CLV 33" EarnedFirstDown="False" PlayDescription="(2:38) 10-K.Holcomb pass to 31-W.Green to CLV 35 for 2 yards (28-I.Bashir, 53-M.Washington)."/><Play Header="Two-Minute Warning"/><Play DownDistanceYardline="2-8-CLV 35" EarnedFirstDown="False" PlayDescription="(2:00) (Shotgun) PENALTY on CLV-10-K.Holcomb, False Start, 5 yards, enforced at CLV 35 - No Play."/><Play DownDistanceYardline="2-13-CLV 30" EarnedFirstDown="False" PlayDescription="(2:00) 10-K.Holcomb pass intended for 86-D.Northcutt INTERCEPTED by 25-N.Harper at CLV 48. 25-N.Harper to CLV 44 for 4 yards (86-D.Northcutt)."/><Play Header="Indianapolis Colts at 1:53"/><Play DownDistanceYardline="1-10-CLV 44" EarnedFirstDown="False" PlayDescription="(1:53) 18-P.Manning pass incomplete to 44-D.Clark."/><Play DownDistanceYardline="2-10-CLV 44" EarnedFirstDown="False" PlayDescription="(1:48) (Shotgun) 18-P.Manning pass intended for 32-E.James INTERCEPTED by 58-B.Taylor at CLV 37. 58-B.Taylor to CLV 37 for no gain (32-E.James)."/><Play Header="Cleveland Browns at 1:42"/><Play DownDistanceYardline="1-10-CLV 37" EarnedFirstDown="False" PlayDescription="(1:42) (Shotgun) 30-J.White left tackle to CLV 43 for 6 yards (98-R.Mathis)."/><Play PlayDescription="PENALTY on CLV-81-Q.Morgan, Offensive Holding, 10 yards, enforced at CLV 41."/><Play DownDistanceYardline="1-16-CLV 31" EarnedFirstDown="False" PlayDescription="(1:35) (Shotgun) 10-K.Holcomb pass to 30-J.White to CLV 36 for 5 yards (90-M.Reagor)."/><Play DownDistanceYardline="2-11-CLV 36" EarnedFirstDown="False" PlayDescription="(1:12) (Shotgun) 10-K.Holcomb pass to 86-D.Northcutt to CLV 40 for 4 yards (27-D.Macklin)."/><Play DownDistanceYardline="3-7-CLV 40" EarnedFirstDown="False" PlayDescription="(:40) (Shotgun) 10-K.Holcomb pass intended for 82-S.Heiden INTERCEPTED by 25-N.Harper at CLV 49. 25-N.Harper to CLV 10 for 39 yards (50-J.Faine)."/><Play Header="Indianapolis Colts at 0:29"/><Play DownDistanceYardline="1-10-CLV 10" EarnedFirstDown="False" PlayDescription="(:29) (Shotgun) 18-P.Manning pass to 88-M.Harrison to CLV 8 for 2 yards (54-A.Davis)."/><Play PlayDescription="Timeout #2 by IND at 00:23."/><Play DownDistanceYardline="2-8-CLV 8" EarnedFirstDown="False" PlayDescription="(:23) (Shotgun) 18-P.Manning pass incomplete to 32-E.James (33-D.McCutcheon)."/><Play DownDistanceYardline="3-8-CLV 8" EarnedFirstDown="False" PlayDescription="(:18) 18-P.Manning pass incomplete to 88-M.Harrison."/><Play PlayDescription="PENALTY on CLV-92-C.Brown, Roughing the Passer, 4 yards, enforced at CLV 8 - No Play." FirstDownType="X9"/><Play DownDistanceYardline="1-4-CLV 4" EarnedFirstDown="True" PlayDescription="(:14) 18-P.Manning pass incomplete to 86-T.Walters (99-O.Roye)."/><Play DownDistanceYardline="2-4-CLV 4" EarnedFirstDown="False" PlayDescription="(:10) 18-P.Manning pass incomplete to 87-R.Wayne."/><Play DownDistanceYardline="3-4-CLV 4" EarnedFirstDown="False" PlayDescription="(:07) (Shotgun) 18-P.Manning pass incomplete to 32-E.James."/><Play DownDistanceYardline="4-4-CLV 4" EarnedFirstDown="False" PlayDescription="(:03) 13-M.Vanderjagt 22 yard field goal is GOOD, Center-48-J.Snow, Holder-17-H.Smith."/><Play Header="IND 3 CLV 3,  6 plays, 6 yards, 1 penalty,  0:29 drive, 15:00 elapsed"/><QuarterSummary Team="Indianapolis Colts" Score="3" TimeOfPossession="8:11" FirstDownsRushing="1" FirstDownsPassing="2" FirstDownsPenalty="1" FirstDownsTotal="4" ThirdDownEfficiency="0/3" FourthDownEfficiency="0/0"/><QuarterSummary Team="Cleveland Browns" Score="3" TimeOfPossession="6:49" FirstDownsRushing="0" FirstDownsPassing="3" FirstDownsPenalty="0" FirstDownsTotal="3" ThirdDownEfficiency="0/2" FourthDownEfficiency="0/0"/></_2ndQuarter><_3rdQuarter><Play Header="CLV elects to Receive, and IND elects to defend the East goal."/><Play Header="13-M.Vanderjagt kicks 61 yards from IND 30 to CLV 9. 84-A.King to CLV 25 for 16 yards (58-G.Brackett)."/><Play Header="Cleveland Browns at 15:00, (1st play from scrimmage 14:56)"/><Play DownDistanceYardline="1-10-CLV 25" EarnedFirstDown="False" PlayDescription="(14:56) 31-W.Green up the middle to CLV 32 for 7 yards (25-N.Harper)."/><Play DownDistanceYardline="2-3-CLV 32" EarnedFirstDown="False" PlayDescription="(14:19) 31-W.Green left tackle to CLV 39 for 7 yards (28-I.Bashir)." FirstDownType="R9"/><Play DownDistanceYardline="1-10-CLV 39" EarnedFirstDown="True" PlayDescription="(13:42) 10-K.Holcomb pass incomplete to 85-K.Johnson."/><Play DownDistanceYardline="2-10-CLV 39" EarnedFirstDown="False" PlayDescription="(13:35) 31-W.Green right guard to CLV 47 for 8 yards (20-M.Doss, 21-W.Harris)."/><Play DownDistanceYardline="3-2-CLV 47" EarnedFirstDown="False" PlayDescription="(12:56) 31-W.Green right tackle to IND 45 for 8 yards (50-D.Thornton)." FirstDownType="R10"/><Play DownDistanceYardline="1-10-IND 45" EarnedFirstDown="True" PlayDescription="(12:15) 31-W.Green right tackle to IND 40 for 5 yards (20-M.Doss)."/><Play PlayDescription="PENALTY on CLV-60-S.O'Hara, Offensive Holding, 10 yards, enforced at IND 45 - No Play."/><Play DownDistanceYardline="1-20-CLV 45" EarnedFirstDown="False" PlayDescription="(11:53) 10-K.Holcomb pass to 85-K.Johnson to IND 45 for 10 yards (21-W.Harris, 94-R.Morris)."/><Play DownDistanceYardline="2-10-IND 45" EarnedFirstDown="False" PlayDescription="(11:12) 30-J.White up the middle to IND 42 for 3 yards (57-J.Nelson, 20-M.Doss)."/><Play DownDistanceYardline="3-7-IND 42" EarnedFirstDown="False" PlayDescription="(10:36) (Shotgun) 10-K.Holcomb pass to 30-J.White to IND 40 for 2 yards (57-J.Nelson)."/><Play DownDistanceYardline="4-5-IND 40" EarnedFirstDown="False" PlayDescription="(9:57) 17-C.Gardocki punts 40 yards to end zone, Center-64-R.Pontbriand, Touchback."/><Play Header="Indianapolis Colts at 9:45"/><Play DownDistanceYardline="1-10-IND 20" EarnedFirstDown="False" PlayDescription="(9:45) 18-P.Manning pass incomplete to 44-D.Clark."/><Play DownDistanceYardline="2-10-IND 20" EarnedFirstDown="False" PlayDescription="(9:40) (Shotgun) 18-P.Manning pass to 32-E.James to IND 29 for 9 yards (33-D.McCutcheon, 59-K.Bentley)."/><Play DownDistanceYardline="3-1-IND 29" EarnedFirstDown="False" PlayDescription="(8:59) 32-E.James right guard to IND 39 for 10 yards (54-A.Davis)." FirstDownType="R10"/><Play DownDistanceYardline="1-10-IND 39" EarnedFirstDown="True" PlayDescription="(8:21) 18-P.Manning pass to 44-D.Clark to CLV 43 for 18 yards (20-E.Little)." FirstDownType="P11"/><Play DownDistanceYardline="1-10-CLV 43" EarnedFirstDown="True" PlayDescription="(7:31) 18-P.Manning pass to 88-M.Harrison to CLV 41 for 2 yards (33-D.McCutcheon)."/><Play DownDistanceYardline="2-8-CLV 41" EarnedFirstDown="False" PlayDescription="(6:50) (Shotgun) 32-E.James up the middle to CLV 38 for 3 yards (99-O.Roye)."/><Play DownDistanceYardline="3-5-CLV 38" EarnedFirstDown="False" PlayDescription="(6:08) (Shotgun) 18-P.Manning pass to 88-M.Harrison to CLV 32 for 6 yards (33-D.McCutcheon)." FirstDownType="P12"/><Play DownDistanceYardline="1-10-CLV 32" EarnedFirstDown="True" PlayDescription="(5:23) 18-P.Manning pass incomplete to 88-M.Harrison."/><Play DownDistanceYardline="2-10-CLV 32" EarnedFirstDown="False" PlayDescription="(5:17) 32-E.James right tackle to CLV 23 for 9 yards (25-C.Crocker)."/><Play DownDistanceYardline="3-1-CLV 23" EarnedFirstDown="False" PlayDescription="(4:35) 32-E.James right guard to CLV 23 for no gain (96-K.Lang)."/><Play DownDistanceYardline="4-1-CLV 23" EarnedFirstDown="False" PlayDescription="(4:35) (Field Goal formation) PENALTY on IND-74-S.Sciullo, False Start, 5 yards, enforced at CLV 23 - No Play."/><Play DownDistanceYardline="4-6-CLV 28" EarnedFirstDown="False" PlayDescription="(3:48) 13-M.Vanderjagt 46 yard field goal is GOOD, Center-48-J.Snow, Holder-17-H.Smith."/><Play Header="IND 6 CLV 3,  11 plays, 52 yards,  6:02 drive, 11:17 elapsed"/><Play Header="13-M.Vanderjagt kicks 68 yards from IND 30 to CLV 2. 81-Q.Morgan to CLV 25 for 23 yards (31-C.Crosby)."/><Play Header="PENALTY on CLV-91-F.Claybrooks, Offensive Holding, 10 yards, enforced at CLV 22."/><Play Header="Cleveland Browns at 3:43, (1st play from scrimmage 3:36)"/><Play DownDistanceYardline="1-10-CLV 12" EarnedFirstDown="False" PlayDescription="(3:36) 10-K.Holcomb pass to 82-S.Heiden to CLV 18 for 6 yards (94-R.Morris, 53-M.Washington)."/><Play DownDistanceYardline="2-4-CLV 18" EarnedFirstDown="False" PlayDescription="(3:04) 31-W.Green left guard to CLV 21 for 3 yards (75-L.Tripplett, 53-M.Washington)."/><Play DownDistanceYardline="3-1-CLV 21" EarnedFirstDown="False" PlayDescription="(2:24) 31-W.Green right guard to CLV 29 for 8 yards (20-M.Doss)." FirstDownType="R11"/><Play DownDistanceYardline="1-10-CLV 29" EarnedFirstDown="True" PlayDescription="(1:48) 10-K.Holcomb pass to 85-K.Johnson to CLV 39 for 10 yards (20-M.Doss)." FirstDownType="P12"/><Play DownDistanceYardline="1-10-CLV 39" EarnedFirstDown="True" PlayDescription="(1:01) 10-K.Holcomb pass incomplete to 31-W.Green."/><Play DownDistanceYardline="2-10-CLV 39" EarnedFirstDown="False" PlayDescription="(:54) 31-W.Green up the middle to CLV 41 for 2 yards (20-M.Doss, 79-R.Brock)."/><Play DownDistanceYardline="3-8-CLV 41" EarnedFirstDown="False" PlayDescription="(:17) (Shotgun) 10-K.Holcomb pass to 30-J.White to IND 42 for 17 yards (25-N.Harper)." FirstDownType="P13"/><QuarterSummary Team="Indianapolis Colts" Score="6" TimeOfPossession="6:02" FirstDownsRushing="1" FirstDownsPassing="2" FirstDownsPenalty="0" FirstDownsTotal="3" ThirdDownEfficiency="2/3" FourthDownEfficiency="0/0"/><QuarterSummary Team="Cleveland Browns" Score="3" TimeOfPossession="8:58" FirstDownsRushing="3" FirstDownsPassing="2" FirstDownsPenalty="0" FirstDownsTotal="5" ThirdDownEfficiency="3/4" FourthDownEfficiency="0/0"/></_3rdQuarter><_4thQuarter><Play Header="Cleveland Browns continued."/><Play DownDistanceYardline="1-10-IND 42" EarnedFirstDown="True" PlayDescription="(15:00) 31-W.Green right tackle pushed ob at IND 31 for 11 yards (21-W.Harris)." FirstDownType="R14"/><Play DownDistanceYardline="1-10-IND 31" EarnedFirstDown="True" PlayDescription="(14:30) PENALTY on CLV-85-K.Johnson, False Start, 5 yards, enforced at IND 31 - No Play."/><Play DownDistanceYardline="1-15-IND 36" EarnedFirstDown="False" PlayDescription="(14:09) 31-W.Green right guard to IND 38 for -2 yards (93-D.Freeney, 90-M.Reagor)."/><Play DownDistanceYardline="2-17-IND 38" EarnedFirstDown="False" PlayDescription="(13:34) (Shotgun) 10-K.Holcomb pass to 87-A.Davis pushed ob at IND 20 for 18 yards (27-D.Macklin)." FirstDownType="P15"/><Play DownDistanceYardline="1-10-IND 20" EarnedFirstDown="True" PlayDescription="(13:07) 31-W.Green right tackle to IND 21 for -1 yards (96-J.Williams)."/><Play DownDistanceYardline="2-11-IND 21" EarnedFirstDown="False" PlayDescription="(12:24) 10-K.Holcomb pass to 82-S.Heiden to IND 14 for 7 yards (21-W.Harris, 50-D.Thornton)."/><Play PlayDescription="PENALTY on IND-79-R.Brock, Defensive Offside, 5 yards, enforced at IND 21 - No Play."/><Play DownDistanceYardline="2-6-IND 16" EarnedFirstDown="False" PlayDescription="(11:54) 10-K.Holcomb pass incomplete to 81-Q.Morgan (25-N.Harper)."/><Play DownDistanceYardline="3-6-IND 16" EarnedFirstDown="False" PlayDescription="(11:49) (Shotgun) 10-K.Holcomb pass to 86-D.Northcutt to IND 8 for 8 yards (21-W.Harris, 20-M.Doss)." FirstDownType="P16"/><Play DownDistanceYardline="1-8-IND 8" EarnedFirstDown="True" PlayDescription="(11:49) PENALTY on CLV-79-B.Stokes, False Start, 5 yards, enforced at IND 8 - No Play."/><Play DownDistanceYardline="1-13-IND 13" EarnedFirstDown="False" PlayDescription="(10:46) 10-K.Holcomb pass to 80-A.Shea to IND 6 for 7 yards (20-M.Doss, 75-L.Tripplett)."/><Play PlayDescription="PENALTY on IND-53-M.Washington, Roughing the Passer, 3 yards, enforced at IND 6. Browns player Scioli injured on the play" FirstDownType="X17"/><Play DownDistanceYardline="1-3-IND 3" EarnedFirstDown="True" PlayDescription="(10:22) 31-W.Green right tackle to IND 3 for no gain (28-I.Bashir)."/><Play DownDistanceYardline="2-3-IND 3" EarnedFirstDown="False" PlayDescription="(9:36) 31-W.Green up the middle to IND 2 for 1 yard (25-N.Harper, 28-I.Bashir)."/><Play DownDistanceYardline="3-2-IND 2" EarnedFirstDown="False" PlayDescription="(8:57) 10-K.Holcomb pass incomplete to 31-W.Green."/><Play DownDistanceYardline="4-2-IND 2" EarnedFirstDown="False" PlayDescription="(8:52) 4-P.Dawson 20 yard field goal is GOOD, Center-64-R.Pontbriand, Holder-17-C.Gardocki."/><Play Header="IND 6 CLV 6,  18 plays, 86 yards, 2 penalties,  9:59 drive,  6:16 elapsed"/><Play Header="4-P.Dawson kicks 51 yards from CLV 30 to IND 19. 43-B.Allen to IND 25 for 6 yards (21-L.Sanders)."/><Play Header="Indianapolis Colts at 8:44, (1st play from scrimmage 8:43)"/><Play DownDistanceYardline="1-10-IND 25" EarnedFirstDown="False" PlayDescription="(8:43) 32-E.James right guard to IND 26 for 1 yard (92-C.Brown)."/><Play DownDistanceYardline="2-9-IND 26" EarnedFirstDown="False" PlayDescription="(8:04) 18-P.Manning pass to 32-E.James to IND 28 for 2 yards (58-B.Taylor)."/><Play DownDistanceYardline="3-7-IND 28" EarnedFirstDown="False" PlayDescription="(7:17) (Shotgun) 18-P.Manning pass to 87-R.Wayne to IND 39 for 11 yards (37-A.Henry)." FirstDownType="P13"/><Play DownDistanceYardline="1-10-IND 39" EarnedFirstDown="True" PlayDescription="(6:32) 32-E.James left tackle to 50 for 11 yards (24-R.Griffith)."/><Play PlayDescription="PENALTY on IND-87-R.Wayne, Offensive Holding, 10 yards, enforced at IND 49."/><Play DownDistanceYardline="1-10-IND 39" EarnedFirstDown="False" PlayDescription="(5:58) (Shotgun) 32-E.James up the middle to IND 38 for -1 yards (99-O.Roye)."/><Play DownDistanceYardline="2-11-IND 38" EarnedFirstDown="False" PlayDescription="(5:19) (Shotgun) 18-P.Manning pass incomplete to 32-E.James (90-M.Word)."/><Play DownDistanceYardline="3-11-IND 38" EarnedFirstDown="False" PlayDescription="(5:16) (Shotgun) 18-P.Manning pass incomplete to 86-T.Walters."/><Play DownDistanceYardline="4-11-IND 38" EarnedFirstDown="False" PlayDescription="(5:09) 17-H.Smith punts 35 yards to CLV 27, Center-48-J.Snow, out of bounds."/><Play Header="Cleveland Browns at 5:02"/><Play DownDistanceYardline="1-10-CLV 27" EarnedFirstDown="False" PlayDescription="(5:02) 31-W.Green right tackle to CLV 42 for 15 yards (21-W.Harris). FUMBLES (21-W.Harris), recovered by CLV-86-D.Northcutt at CLV 45. 86-D.Northcutt to CLV 45 for no gain (25-N.Harper)." FirstDownType="R18"/><Play DownDistanceYardline="1-10-CLV 45" EarnedFirstDown="True" PlayDescription="(4:16) 10-K.Holcomb pass to 31-W.Green pushed ob at IND 49 for 6 yards."/><Play DownDistanceYardline="2-4-IND 49" EarnedFirstDown="False" PlayDescription="(4:12) 10-K.Holcomb pass to 86-D.Northcutt to 50 for -1 yards (25-N.Harper)."/><Play DownDistanceYardline="3-5-50" EarnedFirstDown="False" PlayDescription="(3:34) (Shotgun) 10-K.Holcomb pass to 30-J.White to CLV 45 for -5 yards (57-J.Nelson)."/><Play DownDistanceYardline="4-10-CLV 45" EarnedFirstDown="False" PlayDescription="(2:51) 17-C.Gardocki punts 49 yards to IND 6, Center-64-R.Pontbriand. 84-B.Pyatt to IND 8 for 2 yards (52-B.Boyer, 56-S.Coates)."/><Play Header="Indianapolis Colts at 2:39"/><Play DownDistanceYardline="1-10-IND 8" EarnedFirstDown="False" PlayDescription="(2:39) (Shotgun) 18-P.Manning pass to 88-M.Harrison to IND 19 for 11 yards (58-B.Taylor)." FirstDownType="P14"/><Play DownDistanceYardline="1-10-IND 19" EarnedFirstDown="True" PlayDescription="(2:13) (Shotgun) 18-P.Manning pass to 32-E.James to IND 24 for 5 yards (33-D.McCutcheon)."/><Play Header="Two-Minute Warning"/><Play DownDistanceYardline="2-5-IND 24" EarnedFirstDown="False" PlayDescription="(2:00) (Shotgun) 18-P.Manning pass to 35-R.Williams to IND 34 for 10 yards (54-A.Davis)." FirstDownType="P15"/><Play DownDistanceYardline="1-10-IND 34" EarnedFirstDown="True" PlayDescription="(1:39) (Shotgun) 18-P.Manning pass incomplete to 86-T.Walters."/><Play DownDistanceYardline="2-10-IND 34" EarnedFirstDown="False" PlayDescription="(1:35) (Shotgun) 18-P.Manning pass incomplete to 44-D.Clark."/><Play DownDistanceYardline="3-10-IND 34" EarnedFirstDown="False" PlayDescription="(1:29) (Shotgun) 18-P.Manning pass to 87-R.Wayne to IND 49 for 15 yards (24-R.Griffith)." FirstDownType="P16"/><Play DownDistanceYardline="1-10-IND 49" EarnedFirstDown="True" PlayDescription="(1:09) (Shotgun) 18-P.Manning pass to 88-M.Harrison to CLV 49 for 2 yards (58-B.Taylor)."/><Play DownDistanceYardline="2-8-CLV 49" EarnedFirstDown="False" PlayDescription="(:48) (Shotgun) 18-P.Manning pass to 86-T.Walters to CLV 40 for 9 yards (54-A.Davis)." FirstDownType="P17"/><Play PlayDescription="Timeout #1 by IND at 00:36."/><Play DownDistanceYardline="1-10-CLV 40" EarnedFirstDown="True" PlayDescription="(:36) (Shotgun) 18-P.Manning pass to 86-T.Walters to CLV 32 for 8 yards (54-A.Davis)."/><Play PlayDescription="Timeout #2 by IND at 00:28."/><Play DownDistanceYardline="2-2-CLV 32" EarnedFirstDown="False" PlayDescription="(:28) (Shotgun) 18-P.Manning pass to 88-M.Harrison to CLV 27 for 5 yards (54-A.Davis)." FirstDownType="P18"/><Play PlayDescription="Timeout #3 by IND at 00:06."/><Play PlayDescription="Timeout #1 by CLV at 00:06."/><Play DownDistanceYardline="1-10-CLV 27" EarnedFirstDown="True" PlayDescription="(:06) 13-M.Vanderjagt 45 yard field goal is GOOD, Center-48-J.Snow, Holder-17-H.Smith."/><Play Header="IND 9 CLV 6,  11 plays, 65 yards,  2:38 drive, 14:59 elapsed"/><Play Header="13-M.Vanderjagt kicks 29 yards from IND 30 to CLV 41. 30-J.White to CLV 41 for no gain (58-G.Brackett).
(C.Thompson receives ball and laterals to A.King at CLV 35 who then laterals to J.White)"/><QuarterSummary Team="Indianapolis Colts" Score="9" TimeOfPossession="6:20" FirstDownsRushing="0" FirstDownsPassing="6" FirstDownsPenalty="0" FirstDownsTotal="6" ThirdDownEfficiency="2/3" FourthDownEfficiency="0/0"/><QuarterSummary Team="Cleveland Browns" Score="6" TimeOfPossession="8:40" FirstDownsRushing="2" FirstDownsPassing="2" FirstDownsPenalty="1" FirstDownsTotal="5" ThirdDownEfficiency="1/3" FourthDownEfficiency="0/0"/></_4thQuarter></PlayByPlay></Gamebook>
